{
"meta":{"test_sets":[],"test_metrics":[],"learn_metrics":[{"best_value":"Min","name":"MultiClass"}],"launch_mode":"Train","parameters":"","iteration_count":1000,"learn_sets":["learn"],"name":"experiment"},
"iterations":[
{"learn":[1.832631432],"iteration":0,"passed_time":0.01954305698,"remaining_time":19.52351392},
{"learn":[1.712666891],"iteration":1,"passed_time":0.02973814985,"remaining_time":14.83933678},
{"learn":[1.609940363],"iteration":2,"passed_time":0.03785722645,"remaining_time":12.58121826},
{"learn":[1.52304101],"iteration":3,"passed_time":0.04891679277,"remaining_time":12.1802814},
{"learn":[1.454008798],"iteration":4,"passed_time":0.0579373098,"remaining_time":11.52952465},
{"learn":[1.385171613],"iteration":5,"passed_time":0.06733226038,"remaining_time":11.15471114},
{"learn":[1.323109122],"iteration":6,"passed_time":0.07529655351,"remaining_time":10.68135395},
{"learn":[1.275107756],"iteration":7,"passed_time":0.08339604251,"remaining_time":10.34110927},
{"learn":[1.229148721],"iteration":8,"passed_time":0.09455044129,"remaining_time":10.41105415},
{"learn":[1.183437665],"iteration":9,"passed_time":0.107000694,"remaining_time":10.59306871},
{"learn":[1.143625083],"iteration":10,"passed_time":0.1172663696,"remaining_time":10.54331268},
{"learn":[1.104293145],"iteration":11,"passed_time":0.1287231444,"remaining_time":10.59820555},
{"learn":[1.071050931],"iteration":12,"passed_time":0.1448166235,"remaining_time":10.99492364},
{"learn":[1.039394299],"iteration":13,"passed_time":0.1590604258,"remaining_time":11.20239856},
{"learn":[1.008348203],"iteration":14,"passed_time":0.1704974336,"remaining_time":11.19599814},
{"learn":[0.9820683327],"iteration":15,"passed_time":0.1819233004,"remaining_time":11.18828298},
{"learn":[0.9574982748],"iteration":16,"passed_time":0.1945449668,"remaining_time":11.24927661},
{"learn":[0.9329126069],"iteration":17,"passed_time":0.2071227657,"remaining_time":11.29969755},
{"learn":[0.9111947979],"iteration":18,"passed_time":0.2189249827,"remaining_time":11.30344253},
{"learn":[0.891538135],"iteration":19,"passed_time":0.2281265537,"remaining_time":11.17820113},
{"learn":[0.8709514509],"iteration":20,"passed_time":0.2367118455,"remaining_time":11.0352808},
{"learn":[0.8516735243],"iteration":21,"passed_time":0.246947965,"remaining_time":10.97795953},
{"learn":[0.8347882788],"iteration":22,"passed_time":0.2580982749,"remaining_time":10.96356585},
{"learn":[0.8187447783],"iteration":23,"passed_time":0.2663405905,"remaining_time":10.83118401},
{"learn":[0.8052492218],"iteration":24,"passed_time":0.2800928649,"remaining_time":10.92362173},
{"learn":[0.7889788845],"iteration":25,"passed_time":0.2900785305,"remaining_time":10.86678803},
{"learn":[0.7771909701],"iteration":26,"passed_time":0.298611173,"remaining_time":10.7610619},
{"learn":[0.7657903887],"iteration":27,"passed_time":0.3089348522,"remaining_time":10.72445273},
{"learn":[0.7560467832],"iteration":28,"passed_time":0.3193466771,"remaining_time":10.69260771},
{"learn":[0.7420871411],"iteration":29,"passed_time":0.3282520434,"remaining_time":10.61348274},
{"learn":[0.732554179],"iteration":30,"passed_time":0.3388620663,"remaining_time":10.59217233},
{"learn":[0.7220594675],"iteration":31,"passed_time":0.346903166,"remaining_time":10.49382077},
{"learn":[0.7093610419],"iteration":32,"passed_time":0.3576247006,"remaining_time":10.47948744},
{"learn":[0.6999753936],"iteration":33,"passed_time":0.3666157949,"remaining_time":10.4162017},
{"learn":[0.6896048961],"iteration":34,"passed_time":0.3762236684,"remaining_time":10.373024},
{"learn":[0.6806523693],"iteration":35,"passed_time":0.3874919367,"remaining_time":10.37617297},
{"learn":[0.6681863492],"iteration":36,"passed_time":0.3954541127,"remaining_time":10.29249488},
{"learn":[0.6620787952],"iteration":37,"passed_time":0.4059030782,"remaining_time":10.27575687},
{"learn":[0.6521317512],"iteration":38,"passed_time":0.4149494575,"remaining_time":10.22478022},
{"learn":[0.6439261997],"iteration":39,"passed_time":0.4247792467,"remaining_time":10.19470192},
{"learn":[0.6329595044],"iteration":40,"passed_time":0.435818283,"remaining_time":10.19389594},
{"learn":[0.6254256968],"iteration":41,"passed_time":0.4436978059,"remaining_time":10.12053567},
{"learn":[0.6185070453],"iteration":42,"passed_time":0.45432145,"remaining_time":10.11129367},
{"learn":[0.6126255052],"iteration":43,"passed_time":0.4630754369,"remaining_time":10.06136631},
{"learn":[0.6064259402],"iteration":44,"passed_time":0.4721579974,"remaining_time":10.02024195},
{"learn":[0.5999210663],"iteration":45,"passed_time":0.4830407669,"remaining_time":10.01784547},
{"learn":[0.5948710475],"iteration":46,"passed_time":0.4913831261,"remaining_time":9.963577003},
{"learn":[0.5881033432],"iteration":47,"passed_time":0.5021302444,"remaining_time":9.958916515},
{"learn":[0.5808662031],"iteration":48,"passed_time":0.5103533031,"remaining_time":9.905020229},
{"learn":[0.5747613865],"iteration":49,"passed_time":0.520341472,"remaining_time":9.886487967},
{"learn":[0.5700520261],"iteration":50,"passed_time":0.5299066507,"remaining_time":9.860419834},
{"learn":[0.5635075039],"iteration":51,"passed_time":0.5381019652,"remaining_time":9.81001275},
{"learn":[0.5589332507],"iteration":52,"passed_time":0.5483790961,"remaining_time":9.798396303},
{"learn":[0.5539970432],"iteration":53,"passed_time":0.5561615533,"remaining_time":9.743126472},
{"learn":[0.5477997876],"iteration":54,"passed_time":0.5663798941,"remaining_time":9.731436362},
{"learn":[0.542211347],"iteration":55,"passed_time":0.574277764,"remaining_time":9.680682307},
{"learn":[0.5374332384],"iteration":56,"passed_time":0.5847608907,"remaining_time":9.674202104},
{"learn":[0.5339176974],"iteration":57,"passed_time":0.5924827284,"remaining_time":9.622736726},
{"learn":[0.527820668],"iteration":58,"passed_time":0.6063627107,"remaining_time":9.670971369},
{"learn":[0.5214749395],"iteration":59,"passed_time":0.618743285,"remaining_time":9.693644798},
{"learn":[0.5171147175],"iteration":60,"passed_time":0.6288224733,"remaining_time":9.679742663},
{"learn":[0.5135346449],"iteration":61,"passed_time":0.6380136436,"remaining_time":9.652528996},
{"learn":[0.5090766756],"iteration":62,"passed_time":0.6491341543,"remaining_time":9.654582581},
{"learn":[0.5049210094],"iteration":63,"passed_time":0.6581461638,"remaining_time":9.625387645},
{"learn":[0.5016579364],"iteration":64,"passed_time":0.6713275408,"remaining_time":9.656788471},
{"learn":[0.4986249498],"iteration":65,"passed_time":0.6844448135,"remaining_time":9.685931148},
{"learn":[0.4949797417],"iteration":66,"passed_time":0.6945491755,"remaining_time":9.671856429},
{"learn":[0.4916398732],"iteration":67,"passed_time":0.703096375,"remaining_time":9.636556199},
{"learn":[0.4885925481],"iteration":68,"passed_time":0.7140974926,"remaining_time":9.63514153},
{"learn":[0.4847393578],"iteration":69,"passed_time":0.7226520393,"remaining_time":9.600948522},
{"learn":[0.4829763627],"iteration":70,"passed_time":0.7338525813,"remaining_time":9.602099267},
{"learn":[0.47872607],"iteration":71,"passed_time":0.7454081327,"remaining_time":9.6074826},
{"learn":[0.4759328893],"iteration":72,"passed_time":0.7547824387,"remaining_time":9.584703023},
{"learn":[0.4736202949],"iteration":73,"passed_time":0.765859156,"remaining_time":9.583588898},
{"learn":[0.4707098781],"iteration":74,"passed_time":0.7760335541,"remaining_time":9.5710805},
{"learn":[0.4679159645],"iteration":75,"passed_time":0.7844062996,"remaining_time":9.536729222},
{"learn":[0.4654007988],"iteration":76,"passed_time":0.7956493071,"remaining_time":9.537458577},
{"learn":[0.4630659743],"iteration":77,"passed_time":0.8045230159,"remaining_time":9.509874624},
{"learn":[0.4599056787],"iteration":78,"passed_time":0.8163397266,"remaining_time":9.517074534},
{"learn":[0.4569746433],"iteration":79,"passed_time":0.8273986548,"remaining_time":9.51508453},
{"learn":[0.453767241],"iteration":80,"passed_time":0.8354550892,"remaining_time":9.478805271},
{"learn":[0.4503940727],"iteration":81,"passed_time":0.8464635308,"remaining_time":9.476262454},
{"learn":[0.44774707],"iteration":82,"passed_time":0.8556099387,"remaining_time":9.452943539},
{"learn":[0.442895815],"iteration":83,"passed_time":0.8650304873,"remaining_time":9.432951505},
{"learn":[0.4388997943],"iteration":84,"passed_time":0.8759636802,"remaining_time":9.429491381},
{"learn":[0.4367066422],"iteration":85,"passed_time":0.884351333,"remaining_time":9.398803702},
{"learn":[0.4343291934],"iteration":86,"passed_time":0.8961069323,"remaining_time":9.403972749},
{"learn":[0.4323462599],"iteration":87,"passed_time":0.9073548735,"remaining_time":9.403495962},
{"learn":[0.4287007145],"iteration":88,"passed_time":0.9153348092,"remaining_time":9.369325969},
{"learn":[0.4258033081],"iteration":89,"passed_time":0.92633127,"remaining_time":9.366238397},
{"learn":[0.4231671678],"iteration":90,"passed_time":0.9348626642,"remaining_time":9.338353426},
{"learn":[0.4186054241],"iteration":91,"passed_time":0.9452785089,"remaining_time":9.329487892},
{"learn":[0.416572196],"iteration":92,"passed_time":0.9563629388,"remaining_time":9.327109521},
{"learn":[0.4134400836],"iteration":93,"passed_time":0.9643040658,"remaining_time":9.294249826},
{"learn":[0.4104756847],"iteration":94,"passed_time":0.9758041671,"remaining_time":9.295818645},
{"learn":[0.4070350341],"iteration":95,"passed_time":0.9843955146,"remaining_time":9.269724429},
{"learn":[0.4038514618],"iteration":96,"passed_time":0.9947181634,"remaining_time":9.260108263},
{"learn":[0.4017135213],"iteration":97,"passed_time":1.007020245,"remaining_time":9.268696539},
{"learn":[0.3986407885],"iteration":98,"passed_time":1.017039533,"remaining_time":9.256087064},
{"learn":[0.3967044126],"iteration":99,"passed_time":1.027900489,"remaining_time":9.251104401},
{"learn":[0.3949005672],"iteration":100,"passed_time":1.0386956,"remaining_time":9.245419251},
{"learn":[0.3928799722],"iteration":101,"passed_time":1.046512845,"remaining_time":9.213417011},
{"learn":[0.3911688695],"iteration":102,"passed_time":1.057459468,"remaining_time":9.209137308},
{"learn":[0.3896684163],"iteration":103,"passed_time":1.066641442,"remaining_time":9.189526273},
{"learn":[0.3879934965],"iteration":104,"passed_time":1.077331688,"remaining_time":9.182970102},
{"learn":[0.3856715069],"iteration":105,"passed_time":1.089020235,"remaining_time":9.184755565},
{"learn":[0.3842431397],"iteration":106,"passed_time":1.097868026,"remaining_time":9.162580819},
{"learn":[0.3819288416],"iteration":107,"passed_time":1.108997547,"remaining_time":9.159498256},
{"learn":[0.3801012488],"iteration":108,"passed_time":1.121516596,"remaining_time":9.167626483},
{"learn":[0.3792846287],"iteration":109,"passed_time":1.129624995,"remaining_time":9.139693144},
{"learn":[0.376406756],"iteration":110,"passed_time":1.1400795,"remaining_time":9.130906985},
{"learn":[0.3747502242],"iteration":111,"passed_time":1.150156655,"remaining_time":9.119099191},
{"learn":[0.3731498746],"iteration":112,"passed_time":1.158717595,"remaining_time":9.095420417},
{"learn":[0.3704757135],"iteration":113,"passed_time":1.169696987,"remaining_time":9.090802899},
{"learn":[0.3689474063],"iteration":114,"passed_time":1.178505625,"remaining_time":9.069369372},
{"learn":[0.3666332576],"iteration":115,"passed_time":1.190759618,"remaining_time":9.074409499},
{"learn":[0.3650321811],"iteration":116,"passed_time":1.201965439,"remaining_time":9.07124344},
{"learn":[0.3635239448],"iteration":117,"passed_time":1.209693197,"remaining_time":9.041944066},
{"learn":[0.3622400678],"iteration":118,"passed_time":1.221189355,"remaining_time":9.040906065},
{"learn":[0.3606709477],"iteration":119,"passed_time":1.231510336,"remaining_time":9.031075795},
{"learn":[0.3589165381],"iteration":120,"passed_time":1.239941954,"remaining_time":9.007512208},
{"learn":[0.3568712514],"iteration":121,"passed_time":1.250109809,"remaining_time":8.996691903},
{"learn":[0.3558978817],"iteration":122,"passed_time":1.258194757,"remaining_time":8.971030909},
{"learn":[0.3532547767],"iteration":123,"passed_time":1.269408831,"remaining_time":8.96775916},
{"learn":[0.3524489971],"iteration":124,"passed_time":1.278979206,"remaining_time":8.952854443},
{"learn":[0.349884852],"iteration":125,"passed_time":1.288291739,"remaining_time":8.93624587},
{"learn":[0.3480918372],"iteration":126,"passed_time":1.298682897,"remaining_time":8.927166688},
{"learn":[0.3470178586],"iteration":127,"passed_time":1.308183367,"remaining_time":8.911999189},
{"learn":[0.3452545931],"iteration":128,"passed_time":1.322220792,"remaining_time":8.927552791},
{"learn":[0.343844132],"iteration":129,"passed_time":1.335594763,"remaining_time":8.938211104},
{"learn":[0.342408326],"iteration":130,"passed_time":1.345936392,"remaining_time":8.92838721},
{"learn":[0.3415346048],"iteration":131,"passed_time":1.356869854,"remaining_time":8.922447221},
{"learn":[0.3392051642],"iteration":132,"passed_time":1.369440811,"remaining_time":8.927106643},
{"learn":[0.3375298632],"iteration":133,"passed_time":1.380349118,"remaining_time":8.9207637},
{"learn":[0.3361348748],"iteration":134,"passed_time":1.388075394,"remaining_time":8.893964559},
{"learn":[0.3343200805],"iteration":135,"passed_time":1.39889166,"remaining_time":8.887076431},
{"learn":[0.3331234468],"iteration":136,"passed_time":1.407313877,"remaining_time":8.86505019},
{"learn":[0.3318296715],"iteration":137,"passed_time":1.416660838,"remaining_time":8.84899741},
{"learn":[0.3303818473],"iteration":138,"passed_time":1.427145249,"remaining_time":8.840086755},
{"learn":[0.328969643],"iteration":139,"passed_time":1.434939089,"remaining_time":8.81462583},
{"learn":[0.3272131302],"iteration":140,"passed_time":1.445799283,"remaining_time":8.808096339},
{"learn":[0.3247752237],"iteration":141,"passed_time":1.454325415,"remaining_time":8.78740286},
{"learn":[0.323414352],"iteration":142,"passed_time":1.464213741,"remaining_time":8.775043187},
{"learn":[0.3222723064],"iteration":143,"passed_time":1.474326569,"remaining_time":8.76405238},
{"learn":[0.3213462403],"iteration":144,"passed_time":1.483835197,"remaining_time":8.749510987},
{"learn":[0.320453013],"iteration":145,"passed_time":1.494165071,"remaining_time":8.739842265},
{"learn":[0.319109691],"iteration":146,"passed_time":1.502507998,"remaining_time":8.718634848},
{"learn":[0.3186241904],"iteration":147,"passed_time":1.513487073,"remaining_time":8.712776935},
{"learn":[0.3165793429],"iteration":148,"passed_time":1.522619519,"remaining_time":8.69630343},
{"learn":[0.3159503539],"iteration":149,"passed_time":1.532154313,"remaining_time":8.682207776},
{"learn":[0.3150606096],"iteration":150,"passed_time":1.543052401,"remaining_time":8.675837672},
{"learn":[0.3139058763],"iteration":151,"passed_time":1.551876725,"remaining_time":8.657838573},
{"learn":[0.3124440085],"iteration":152,"passed_time":1.561656921,"remaining_time":8.645251059},
{"learn":[0.3112910742],"iteration":153,"passed_time":1.570137459,"remaining_time":8.625560326},
{"learn":[0.3102598828],"iteration":154,"passed_time":1.57934578,"remaining_time":8.609981834},
{"learn":[0.3091047885],"iteration":155,"passed_time":1.590148509,"remaining_time":8.603111165},
{"learn":[0.3078409935],"iteration":156,"passed_time":1.60071001,"remaining_time":8.59489515},
{"learn":[0.3068445458],"iteration":157,"passed_time":1.611629406,"remaining_time":8.58855671},
{"learn":[0.3052256795],"iteration":158,"passed_time":1.624092781,"remaining_time":8.590327223},
{"learn":[0.3037599044],"iteration":159,"passed_time":1.633118186,"remaining_time":8.573870476},
{"learn":[0.302497442],"iteration":160,"passed_time":1.644400335,"remaining_time":8.569266344},
{"learn":[0.301540664],"iteration":161,"passed_time":1.655235106,"remaining_time":8.56226555},
{"learn":[0.3005565528],"iteration":162,"passed_time":1.662682145,"remaining_time":8.537821811},
{"learn":[0.2999403702],"iteration":163,"passed_time":1.673263309,"remaining_time":8.529561744},
{"learn":[0.2992408363],"iteration":164,"passed_time":1.681563509,"remaining_time":8.509730485},
{"learn":[0.2979964092],"iteration":165,"passed_time":1.692534404,"remaining_time":8.503455982},
{"learn":[0.296883964],"iteration":166,"passed_time":1.701644156,"remaining_time":8.487841806},
{"learn":[0.2957614335],"iteration":167,"passed_time":1.710669651,"remaining_time":8.471887796},
{"learn":[0.2942306257],"iteration":168,"passed_time":1.721692225,"remaining_time":8.465835732},
{"learn":[0.293329363],"iteration":169,"passed_time":1.729508596,"remaining_time":8.444071381},
{"learn":[0.2918308697],"iteration":170,"passed_time":1.740483589,"remaining_time":8.437783012},
{"learn":[0.2908723351],"iteration":171,"passed_time":1.749452748,"remaining_time":8.421784157},
{"learn":[0.2889432614],"iteration":172,"passed_time":1.758196689,"remaining_time":8.404789952},
{"learn":[0.2883376614],"iteration":173,"passed_time":1.768667839,"remaining_time":8.396089856},
{"learn":[0.2870908909],"iteration":174,"passed_time":1.777591276,"remaining_time":8.38007316},
{"learn":[0.2856331929],"iteration":175,"passed_time":1.788658405,"remaining_time":8.374173442},
{"learn":[0.2846258135],"iteration":176,"passed_time":1.797445251,"remaining_time":8.357612664},
{"learn":[0.2832541509],"iteration":177,"passed_time":1.807367105,"remaining_time":8.346380674},
{"learn":[0.2817903789],"iteration":178,"passed_time":1.817669834,"remaining_time":8.336910246},
{"learn":[0.2810578352],"iteration":179,"passed_time":1.827363523,"remaining_time":8.324656049},
{"learn":[0.2797528303],"iteration":180,"passed_time":1.83861757,"remaining_time":8.31949055},
{"learn":[0.2783566081],"iteration":181,"passed_time":1.849450804,"remaining_time":8.312366803},
{"learn":[0.2772644065],"iteration":182,"passed_time":1.857208728,"remaining_time":8.291472846},
{"learn":[0.2758007347],"iteration":183,"passed_time":1.867583421,"remaining_time":8.282326477},
{"learn":[0.2749638505],"iteration":184,"passed_time":1.875725604,"remaining_time":8.263331717},
{"learn":[0.2736447031],"iteration":185,"passed_time":1.886188693,"remaining_time":8.25461073},
{"learn":[0.2728500055],"iteration":186,"passed_time":1.894884222,"remaining_time":8.238186482},
{"learn":[0.2715511879],"iteration":187,"passed_time":1.904109599,"remaining_time":8.224132947},
{"learn":[0.2700011379],"iteration":188,"passed_time":1.914032633,"remaining_time":8.213124155},
{"learn":[0.2688565333],"iteration":189,"passed_time":1.922090595,"remaining_time":8.194175694},
{"learn":[0.2678829294],"iteration":190,"passed_time":1.933179381,"remaining_time":8.188178635},
{"learn":[0.2667928827],"iteration":191,"passed_time":1.941674274,"remaining_time":8.171212569},
{"learn":[0.2655979631],"iteration":192,"passed_time":1.951204223,"remaining_time":8.158662218},
{"learn":[0.2647534366],"iteration":193,"passed_time":1.960293719,"remaining_time":8.144313079},
{"learn":[0.2633813927],"iteration":194,"passed_time":1.969892869,"remaining_time":8.132121842},
{"learn":[0.2623138992],"iteration":195,"passed_time":1.981022165,"remaining_time":8.126233779},
{"learn":[0.260182324],"iteration":196,"passed_time":1.989381659,"remaining_time":8.109002397},
{"learn":[0.259220614],"iteration":197,"passed_time":2.000036569,"remaining_time":8.101158222},
{"learn":[0.2587030744],"iteration":198,"passed_time":2.00938775,"remaining_time":8.088038131},
{"learn":[0.2575071051],"iteration":199,"passed_time":2.021358069,"remaining_time":8.085432275},
{"learn":[0.256068886],"iteration":200,"passed_time":2.032720738,"remaining_time":8.080317761},
{"learn":[0.2550561717],"iteration":201,"passed_time":2.041664372,"remaining_time":8.065584993},
{"learn":[0.2546826417],"iteration":202,"passed_time":2.05045945,"remaining_time":8.050326019},
{"learn":[0.2534648678],"iteration":203,"passed_time":2.06163322,"remaining_time":8.044411976},
{"learn":[0.25281077],"iteration":204,"passed_time":2.069975291,"remaining_time":8.027465153},
{"learn":[0.2518496426],"iteration":205,"passed_time":2.079873293,"remaining_time":8.016599002},
{"learn":[0.2512867113],"iteration":206,"passed_time":2.090319269,"remaining_time":8.007841451},
{"learn":[0.2503287839],"iteration":207,"passed_time":2.101776368,"remaining_time":8.00291771},
{"learn":[0.2496909079],"iteration":208,"passed_time":2.112239387,"remaining_time":7.994169163},
{"learn":[0.2485276602],"iteration":209,"passed_time":2.120765707,"remaining_time":7.978118612},
{"learn":[0.247324858],"iteration":210,"passed_time":2.130780935,"remaining_time":7.967706907},
{"learn":[0.246492635],"iteration":211,"passed_time":2.13970052,"remaining_time":7.953226462},
{"learn":[0.2456633805],"iteration":212,"passed_time":2.152629828,"remaining_time":7.953613497},
{"learn":[0.2450655321],"iteration":213,"passed_time":2.164524349,"remaining_time":7.950075413},
{"learn":[0.2439630622],"iteration":214,"passed_time":2.174839927,"remaining_time":7.940694616},
{"learn":[0.2427048862],"iteration":215,"passed_time":2.183084282,"remaining_time":7.923787395},
{"learn":[0.2419979489],"iteration":216,"passed_time":2.193811411,"remaining_time":7.915918592},
{"learn":[0.2413540144],"iteration":217,"passed_time":2.202842222,"remaining_time":7.901938614},
{"learn":[0.2406825916],"iteration":218,"passed_time":2.212974596,"remaining_time":7.891932234},
{"learn":[0.2398661075],"iteration":219,"passed_time":2.223555893,"remaining_time":7.883516347},
{"learn":[0.2392264318],"iteration":220,"passed_time":2.231425664,"remaining_time":7.865523042},
{"learn":[0.2382537938],"iteration":221,"passed_time":2.242377344,"remaining_time":7.858421503},
{"learn":[0.2375782231],"iteration":222,"passed_time":2.251528325,"remaining_time":7.845011249},
{"learn":[0.2371045285],"iteration":223,"passed_time":2.260377758,"remaining_time":7.830594375},
{"learn":[0.235758213],"iteration":224,"passed_time":2.270811112,"remaining_time":7.821682718},
{"learn":[0.2352959456],"iteration":225,"passed_time":2.27929091,"remaining_time":7.806067099},
{"learn":[0.2347947475],"iteration":226,"passed_time":2.290681749,"remaining_time":7.800427278},
{"learn":[0.2340981619],"iteration":227,"passed_time":2.299146883,"remaining_time":7.784830673},
{"learn":[0.2330349791],"iteration":228,"passed_time":2.312233823,"remaining_time":7.784857108},
{"learn":[0.2321432142],"iteration":229,"passed_time":2.323510871,"remaining_time":7.778710306},
{"learn":[0.231155229],"iteration":230,"passed_time":2.333065492,"remaining_time":7.766785123},
{"learn":[0.2302729715],"iteration":231,"passed_time":2.343333664,"remaining_time":7.757242473},
{"learn":[0.2293014404],"iteration":232,"passed_time":2.35445443,"remaining_time":7.750500204},
{"learn":[0.2284684167],"iteration":233,"passed_time":2.363007858,"remaining_time":7.735316322},
{"learn":[0.2278662703],"iteration":234,"passed_time":2.373938434,"remaining_time":7.727927242},
{"learn":[0.2270730307],"iteration":235,"passed_time":2.383949387,"remaining_time":7.717531067},
{"learn":[0.2267779343],"iteration":236,"passed_time":2.392692538,"remaining_time":7.703056567},
{"learn":[0.2261933479],"iteration":237,"passed_time":2.403429094,"remaining_time":7.695012477},
{"learn":[0.2251603522],"iteration":238,"passed_time":2.4120323,"remaining_time":7.680153055},
{"learn":[0.2248464593],"iteration":239,"passed_time":2.42180648,"remaining_time":7.669053852},
{"learn":[0.2236653398],"iteration":240,"passed_time":2.431161753,"remaining_time":7.656646351},
{"learn":[0.2227653148],"iteration":241,"passed_time":2.440728856,"remaining_time":7.644927574},
{"learn":[0.2220961288],"iteration":242,"passed_time":2.45128747,"remaining_time":7.636315286},
{"learn":[0.2214299852],"iteration":243,"passed_time":2.460121876,"remaining_time":7.622344829},
{"learn":[0.2206520869],"iteration":244,"passed_time":2.471285802,"remaining_time":7.615595023},
{"learn":[0.2198365832],"iteration":245,"passed_time":2.480995332,"remaining_time":7.604351547},
{"learn":[0.2192542146],"iteration":246,"passed_time":2.489305699,"remaining_time":7.588855027},
{"learn":[0.2186586114],"iteration":247,"passed_time":2.499572508,"remaining_time":7.579348896},
{"learn":[0.2181050475],"iteration":248,"passed_time":2.508383715,"remaining_time":7.565446466},
{"learn":[0.2177611712],"iteration":249,"passed_time":2.518905911,"remaining_time":7.556717732},
{"learn":[0.2171803101],"iteration":250,"passed_time":2.526554259,"remaining_time":7.539398965},
{"learn":[0.2164850946],"iteration":251,"passed_time":2.53773267,"remaining_time":7.532635068},
{"learn":[0.2161092457],"iteration":252,"passed_time":2.546380297,"remaining_time":7.518363961},
{"learn":[0.2154068261],"iteration":253,"passed_time":2.554974778,"remaining_time":7.503981041},
{"learn":[0.214587527],"iteration":254,"passed_time":2.565598092,"remaining_time":7.495570897},
{"learn":[0.2139235268],"iteration":255,"passed_time":2.575195749,"remaining_time":7.484162645},
{"learn":[0.2132073138],"iteration":256,"passed_time":2.58566732,"remaining_time":7.475295015},
{"learn":[0.2126808105],"iteration":257,"passed_time":2.59586613,"remaining_time":7.465630499},
{"learn":[0.2116807869],"iteration":258,"passed_time":2.605372732,"remaining_time":7.453981446},
{"learn":[0.2106477191],"iteration":259,"passed_time":2.615677391,"remaining_time":7.444620267},
{"learn":[0.2100603296],"iteration":260,"passed_time":2.625096224,"remaining_time":7.432743715},
{"learn":[0.2094583973],"iteration":261,"passed_time":2.636640565,"remaining_time":7.426873042},
{"learn":[0.2087545732],"iteration":262,"passed_time":2.647667636,"remaining_time":7.419509686},
{"learn":[0.2080540501],"iteration":263,"passed_time":2.65594131,"remaining_time":7.404442439},
{"learn":[0.2077107561],"iteration":264,"passed_time":2.666801814,"remaining_time":7.396601256},
{"learn":[0.2068337571],"iteration":265,"passed_time":2.676649182,"remaining_time":7.385941728},
{"learn":[0.2062004695],"iteration":266,"passed_time":2.684989262,"remaining_time":7.371150297},
{"learn":[0.2060258715],"iteration":267,"passed_time":2.695781419,"remaining_time":7.363104473},
{"learn":[0.2053280883],"iteration":268,"passed_time":2.704616103,"remaining_time":7.349718852},
{"learn":[0.2046248098],"iteration":269,"passed_time":2.714760488,"remaining_time":7.339907987},
{"learn":[0.2039799934],"iteration":270,"passed_time":2.725938357,"remaining_time":7.33287477},
{"learn":[0.2030161056],"iteration":271,"passed_time":2.734144063,"remaining_time":7.317856167},
{"learn":[0.2019373289],"iteration":272,"passed_time":2.744052991,"remaining_time":7.307423166},
{"learn":[0.2016396873],"iteration":273,"passed_time":2.75187663,"remaining_time":7.291468736},
{"learn":[0.2003598076],"iteration":274,"passed_time":2.76298118,"remaining_time":7.284223111},
{"learn":[0.1997187482],"iteration":275,"passed_time":2.770780159,"remaining_time":7.268278388},
{"learn":[0.198699986],"iteration":276,"passed_time":2.781035305,"remaining_time":7.258803341},
{"learn":[0.1977793626],"iteration":277,"passed_time":2.791075895,"remaining_time":7.248765455},
{"learn":[0.1974648397],"iteration":278,"passed_time":2.799874509,"remaining_time":7.235517998},
{"learn":[0.1963160647],"iteration":279,"passed_time":2.809783953,"remaining_time":7.225158737},
{"learn":[0.1953307671],"iteration":280,"passed_time":2.818863618,"remaining_time":7.212679506},
{"learn":[0.1948604743],"iteration":281,"passed_time":2.829090996,"remaining_time":7.203146578},
{"learn":[0.1945245342],"iteration":282,"passed_time":2.838165551,"remaining_time":7.190687986},
{"learn":[0.1938355089],"iteration":283,"passed_time":2.846722992,"remaining_time":7.176949514},
{"learn":[0.1934714101],"iteration":284,"passed_time":2.859335995,"remaining_time":7.173421883},
{"learn":[0.1928938287],"iteration":285,"passed_time":2.868970839,"remaining_time":7.162395731},
{"learn":[0.1923367195],"iteration":286,"passed_time":2.87966224,"remaining_time":7.154004102},
{"learn":[0.1915431918],"iteration":287,"passed_time":2.890765158,"remaining_time":7.146613862},
{"learn":[0.1913551238],"iteration":288,"passed_time":2.899626529,"remaining_time":7.133683259},
{"learn":[0.1910065674],"iteration":289,"passed_time":2.909766114,"remaining_time":7.123910141},
{"learn":[0.1905400121],"iteration":290,"passed_time":2.920422444,"remaining_time":7.115393515},
{"learn":[0.190018551],"iteration":291,"passed_time":2.928185527,"remaining_time":7.0998471},
{"learn":[0.1895239427],"iteration":292,"passed_time":2.93857592,"remaining_time":7.090693432},
{"learn":[0.1891469797],"iteration":293,"passed_time":2.946958965,"remaining_time":7.076710985},
{"learn":[0.1884536928],"iteration":294,"passed_time":2.959603487,"remaining_time":7.072950707},
{"learn":[0.187814498],"iteration":295,"passed_time":2.970155927,"remaining_time":7.064154636},
{"learn":[0.1875745929],"iteration":296,"passed_time":2.979181767,"remaining_time":7.051733274},
{"learn":[0.1867054007],"iteration":297,"passed_time":2.990000534,"remaining_time":7.043558306},
{"learn":[0.1860173774],"iteration":298,"passed_time":2.998915813,"remaining_time":7.030902959},
{"learn":[0.1854472277],"iteration":299,"passed_time":3.008707111,"remaining_time":7.020316593},
{"learn":[0.1848878308],"iteration":300,"passed_time":3.020254302,"remaining_time":7.013813146},
{"learn":[0.1840787701],"iteration":301,"passed_time":3.03030372,"remaining_time":7.003814558},
{"learn":[0.1834120557],"iteration":302,"passed_time":3.04114249,"remaining_time":6.995631404},
{"learn":[0.1830167687],"iteration":303,"passed_time":3.05275223,"remaining_time":6.989195895},
{"learn":[0.182747546],"iteration":304,"passed_time":3.061386254,"remaining_time":6.975945726},
{"learn":[0.1823625314],"iteration":305,"passed_time":3.072457971,"remaining_time":6.968254352},
{"learn":[0.1820180045],"iteration":306,"passed_time":3.080862744,"remaining_time":6.954520787},
{"learn":[0.1816444348],"iteration":307,"passed_time":3.090026046,"remaining_time":6.942526051},
{"learn":[0.1809544547],"iteration":308,"passed_time":3.09922564,"remaining_time":6.9306308},
{"learn":[0.1805559893],"iteration":309,"passed_time":3.107464365,"remaining_time":6.916614231},
{"learn":[0.180093739],"iteration":310,"passed_time":3.118079675,"remaining_time":6.907899987},
{"learn":[0.1796015668],"iteration":311,"passed_time":3.126485581,"remaining_time":6.894301538},
{"learn":[0.1787600217],"iteration":312,"passed_time":3.137311364,"remaining_time":6.886047627},
{"learn":[0.1780107642],"iteration":313,"passed_time":3.147099752,"remaining_time":6.875510924},
{"learn":[0.1776697043],"iteration":314,"passed_time":3.156325927,"remaining_time":6.86375638},
{"learn":[0.1767808631],"iteration":315,"passed_time":3.167192255,"remaining_time":6.855568045},
{"learn":[0.1763642746],"iteration":316,"passed_time":3.175079253,"remaining_time":6.840943626},
{"learn":[0.1755788691],"iteration":317,"passed_time":3.185979891,"remaining_time":6.832824798},
{"learn":[0.1753207457],"iteration":318,"passed_time":3.194162724,"remaining_time":6.818886568},
{"learn":[0.1747156944],"iteration":319,"passed_time":3.203773943,"remaining_time":6.80801963},
{"learn":[0.1743897735],"iteration":320,"passed_time":3.214955184,"remaining_time":6.800481527},
{"learn":[0.1736387868],"iteration":321,"passed_time":3.223258925,"remaining_time":6.78686196},
{"learn":[0.1729341005],"iteration":322,"passed_time":3.233318079,"remaining_time":6.776954612},
{"learn":[0.1724883317],"iteration":323,"passed_time":3.241732887,"remaining_time":6.76361553},
{"learn":[0.1721303208],"iteration":324,"passed_time":3.252441025,"remaining_time":6.755069821},
{"learn":[0.1716290587],"iteration":325,"passed_time":3.263132965,"remaining_time":6.746477357},
{"learn":[0.1712363391],"iteration":326,"passed_time":3.270853393,"remaining_time":6.731756372},
{"learn":[0.170661681],"iteration":327,"passed_time":3.283180742,"remaining_time":6.726516643},
{"learn":[0.1704389101],"iteration":328,"passed_time":3.292545705,"remaining_time":6.715192001},
{"learn":[0.1700192327],"iteration":329,"passed_time":3.301047063,"remaining_time":6.702125856},
{"learn":[0.1697228633],"iteration":330,"passed_time":3.310283688,"remaining_time":6.690573376},
{"learn":[0.1694451081],"iteration":331,"passed_time":3.318895188,"remaining_time":6.677777066},
{"learn":[0.1689837583],"iteration":332,"passed_time":3.329942485,"remaining_time":6.669884796},
{"learn":[0.1686890035],"iteration":333,"passed_time":3.33799814,"remaining_time":6.656008267},
{"learn":[0.1682316919],"iteration":334,"passed_time":3.34800074,"remaining_time":6.64603132},
{"learn":[0.1677059248],"iteration":335,"passed_time":3.357406353,"remaining_time":6.63487446},
{"learn":[0.1673963199],"iteration":336,"passed_time":3.366685637,"remaining_time":6.623479459},
{"learn":[0.167032273],"iteration":337,"passed_time":3.377530427,"remaining_time":6.615163144},
{"learn":[0.166676183],"iteration":338,"passed_time":3.385575878,"remaining_time":6.601373615},
{"learn":[0.1663568959],"iteration":339,"passed_time":3.396135114,"remaining_time":6.592497575},
{"learn":[0.1656891383],"iteration":340,"passed_time":3.404332915,"remaining_time":6.579048068},
{"learn":[0.1653994089],"iteration":341,"passed_time":3.414391501,"remaining_time":6.569209379},
{"learn":[0.1651355707],"iteration":342,"passed_time":3.425288937,"remaining_time":6.560976186},
{"learn":[0.1647863916],"iteration":343,"passed_time":3.43304546,"remaining_time":6.546737854},
{"learn":[0.1645059296],"iteration":344,"passed_time":3.443553105,"remaining_time":6.537760243},
{"learn":[0.1643273187],"iteration":345,"passed_time":3.451653326,"remaining_time":6.524223339},
{"learn":[0.1640071236],"iteration":346,"passed_time":3.462498253,"remaining_time":6.51588288},
{"learn":[0.1636931108],"iteration":347,"passed_time":3.470912062,"remaining_time":6.502973173},
{"learn":[0.1631947785],"iteration":348,"passed_time":3.4797044,"remaining_time":6.490795314},
{"learn":[0.1627474719],"iteration":349,"passed_time":3.490768429,"remaining_time":6.482855654},
{"learn":[0.1620906677],"iteration":350,"passed_time":3.499641908,"remaining_time":6.470847858},
{"learn":[0.1616407378],"iteration":351,"passed_time":3.509907078,"remaining_time":6.461419847},
{"learn":[0.1611537199],"iteration":352,"passed_time":3.51806863,"remaining_time":6.448131455},
{"learn":[0.1603788062],"iteration":353,"passed_time":3.528331692,"remaining_time":6.438706986},
{"learn":[0.1598433578],"iteration":354,"passed_time":3.538136991,"remaining_time":6.428446082},
{"learn":[0.1594599966],"iteration":355,"passed_time":3.546219561,"remaining_time":6.415071341},
{"learn":[0.1589548232],"iteration":356,"passed_time":3.557014696,"remaining_time":6.406611903},
{"learn":[0.1584392427],"iteration":357,"passed_time":3.565026684,"remaining_time":6.393148411},
{"learn":[0.158204805],"iteration":358,"passed_time":3.575873395,"remaining_time":6.38477673},
{"learn":[0.1578270628],"iteration":359,"passed_time":3.584524795,"remaining_time":6.372488524},
{"learn":[0.1574407414],"iteration":360,"passed_time":3.594381832,"remaining_time":6.362354544},
{"learn":[0.1569591093],"iteration":361,"passed_time":3.605031105,"remaining_time":6.353618356},
{"learn":[0.1566163848],"iteration":362,"passed_time":3.613218614,"remaining_time":6.340551673},
{"learn":[0.1561886845],"iteration":363,"passed_time":3.624167555,"remaining_time":6.332336717},
{"learn":[0.1557311895],"iteration":364,"passed_time":3.631912271,"remaining_time":6.318532307},
{"learn":[0.1553057639],"iteration":365,"passed_time":3.642534172,"remaining_time":6.309744986},
{"learn":[0.1549033371],"iteration":366,"passed_time":3.652198112,"remaining_time":6.29929538},
{"learn":[0.1545862194],"iteration":367,"passed_time":3.660020006,"remaining_time":6.285686533},
{"learn":[0.154238277],"iteration":368,"passed_time":3.670186178,"remaining_time":6.276117827},
{"learn":[0.1537253153],"iteration":369,"passed_time":3.677701239,"remaining_time":6.26203184},
{"learn":[0.1530046933],"iteration":370,"passed_time":3.68863957,"remaining_time":6.253785147},
{"learn":[0.1524203452],"iteration":371,"passed_time":3.697265029,"remaining_time":6.241619457},
{"learn":[0.1520994579],"iteration":372,"passed_time":3.707025651,"remaining_time":6.231380919},
{"learn":[0.1517056985],"iteration":373,"passed_time":3.716268161,"remaining_time":6.220277725},
{"learn":[0.1511943319],"iteration":374,"passed_time":3.725346029,"remaining_time":6.208910048},
{"learn":[0.1507739722],"iteration":375,"passed_time":3.736249614,"remaining_time":6.200584465},
{"learn":[0.1505477439],"iteration":376,"passed_time":3.74426441,"remaining_time":6.187471426},
{"learn":[0.1501931172],"iteration":377,"passed_time":3.754376244,"remaining_time":6.177836042},
{"learn":[0.1495589672],"iteration":378,"passed_time":3.762795089,"remaining_time":6.165424144},
{"learn":[0.1491859777],"iteration":379,"passed_time":3.772381171,"remaining_time":6.154937701},
{"learn":[0.1487400315],"iteration":380,"passed_time":3.784005586,"remaining_time":6.147767605},
{"learn":[0.1483064968],"iteration":381,"passed_time":3.793143101,"remaining_time":6.136550881},
{"learn":[0.1479105226],"iteration":382,"passed_time":3.803912913,"remaining_time":6.127974588},
{"learn":[0.1476251301],"iteration":383,"passed_time":3.812230792,"remaining_time":6.115453562},
{"learn":[0.1473018386],"iteration":384,"passed_time":3.82107032,"remaining_time":6.103787654},
{"learn":[0.1469546126],"iteration":385,"passed_time":3.831329316,"remaining_time":6.094394301},
{"learn":[0.1464113806],"iteration":386,"passed_time":3.84046629,"remaining_time":6.083219215},
{"learn":[0.1459995382],"iteration":387,"passed_time":3.851236844,"remaining_time":6.07463131},
{"learn":[0.1456113303],"iteration":388,"passed_time":3.859417405,"remaining_time":6.061964098},
{"learn":[0.1453509022],"iteration":389,"passed_time":3.869914577,"remaining_time":6.052943313},
{"learn":[0.1448447649],"iteration":390,"passed_time":3.881055142,"remaining_time":6.044917088},
{"learn":[0.1444542161],"iteration":391,"passed_time":3.889756862,"remaining_time":6.033092275},
{"learn":[0.1438581253],"iteration":392,"passed_time":3.900036237,"remaining_time":6.023720091},
{"learn":[0.1433949056],"iteration":393,"passed_time":3.908154194,"remaining_time":6.011018887},
{"learn":[0.1430512827],"iteration":394,"passed_time":3.918171782,"remaining_time":6.00125045},
{"learn":[0.1425908693],"iteration":395,"passed_time":3.927802309,"remaining_time":5.990890391},
{"learn":[0.1422866461],"iteration":396,"passed_time":3.937101312,"remaining_time":5.980030457},
{"learn":[0.1419484653],"iteration":397,"passed_time":3.947576708,"remaining_time":5.970957734},
{"learn":[0.1414882758],"iteration":398,"passed_time":3.955847466,"remaining_time":5.95855721},
{"learn":[0.1413414694],"iteration":399,"passed_time":3.966238014,"remaining_time":5.94935702},
{"learn":[0.1408834771],"iteration":400,"passed_time":3.974730048,"remaining_time":5.937314959},
{"learn":[0.1405804912],"iteration":401,"passed_time":3.984064282,"remaining_time":5.926543385},
{"learn":[0.1402451266],"iteration":402,"passed_time":3.996128721,"remaining_time":5.91982344},
{"learn":[0.1399674333],"iteration":403,"passed_time":4.005069328,"remaining_time":5.908468613},
{"learn":[0.1397155076],"iteration":404,"passed_time":4.015582755,"remaining_time":5.899436393},
{"learn":[0.1393020401],"iteration":405,"passed_time":4.026003847,"remaining_time":5.890261786},
{"learn":[0.1389444671],"iteration":406,"passed_time":4.035814205,"remaining_time":5.880191212},
{"learn":[0.1385451489],"iteration":407,"passed_time":4.047465955,"remaining_time":5.872793739},
{"learn":[0.1380673874],"iteration":408,"passed_time":4.056963954,"remaining_time":5.862263317},
{"learn":[0.1375590091],"iteration":409,"passed_time":4.066483475,"remaining_time":5.851768903},
{"learn":[0.1372519971],"iteration":410,"passed_time":4.077243282,"remaining_time":5.843056674},
{"learn":[0.1370187004],"iteration":411,"passed_time":4.086317966,"remaining_time":5.831929525},
{"learn":[0.1365836957],"iteration":412,"passed_time":4.096284673,"remaining_time":5.822080152},
{"learn":[0.1362795879],"iteration":413,"passed_time":4.104941805,"remaining_time":5.810376564},
{"learn":[0.1360578879],"iteration":414,"passed_time":4.115647503,"remaining_time":5.801575396},
{"learn":[0.1358426599],"iteration":415,"passed_time":4.126464882,"remaining_time":5.792921853},
{"learn":[0.1355871799],"iteration":416,"passed_time":4.134861403,"remaining_time":5.780873376},
{"learn":[0.1349325537],"iteration":417,"passed_time":4.145448896,"remaining_time":5.771892961},
{"learn":[0.1345911021],"iteration":418,"passed_time":4.154235638,"remaining_time":5.760407889},
{"learn":[0.1344126855],"iteration":419,"passed_time":4.163916229,"remaining_time":5.750170031},
{"learn":[0.1337697341],"iteration":420,"passed_time":4.175296865,"remaining_time":5.742272885},
{"learn":[0.1334301155],"iteration":421,"passed_time":4.183178862,"remaining_time":5.729567257},
{"learn":[0.1330834506],"iteration":422,"passed_time":4.193718685,"remaining_time":5.720509885},
{"learn":[0.1326434653],"iteration":423,"passed_time":4.201805876,"remaining_time":5.708113643},
{"learn":[0.1325122134],"iteration":424,"passed_time":4.211916843,"remaining_time":5.698475729},
{"learn":[0.1322731995],"iteration":425,"passed_time":4.222246239,"remaining_time":5.689129909},
{"learn":[0.1318735184],"iteration":426,"passed_time":4.231685135,"remaining_time":5.678584503},
{"learn":[0.1315215432],"iteration":427,"passed_time":4.243378121,"remaining_time":5.671056741},
{"learn":[0.1313170588],"iteration":428,"passed_time":4.254465647,"remaining_time":5.662703693},
{"learn":[0.1309489906],"iteration":429,"passed_time":4.266310268,"remaining_time":5.655341518},
{"learn":[0.1307656815],"iteration":430,"passed_time":4.27823263,"remaining_time":5.648061175},
{"learn":[0.1305599165],"iteration":431,"passed_time":4.29101384,"remaining_time":5.641888567},
{"learn":[0.1303114026],"iteration":432,"passed_time":4.301902244,"remaining_time":5.633206864},
{"learn":[0.13012781],"iteration":433,"passed_time":4.313807256,"remaining_time":5.625840799},
{"learn":[0.1297560729],"iteration":434,"passed_time":4.326910493,"remaining_time":5.620010181},
{"learn":[0.1296257406],"iteration":435,"passed_time":4.339394007,"remaining_time":5.613344541},
{"learn":[0.1291525654],"iteration":436,"passed_time":4.350758389,"remaining_time":5.605210465},
{"learn":[0.1288491535],"iteration":437,"passed_time":4.361355988,"remaining_time":5.596077775},
{"learn":[0.1284327461],"iteration":438,"passed_time":4.372148238,"remaining_time":5.587187156},
{"learn":[0.128047333],"iteration":439,"passed_time":4.380937048,"remaining_time":5.575738061},
{"learn":[0.127826687],"iteration":440,"passed_time":4.390828921,"remaining_time":5.565699244},
{"learn":[0.1275726389],"iteration":441,"passed_time":4.401650168,"remaining_time":5.556834375},
{"learn":[0.1272837741],"iteration":442,"passed_time":4.410439056,"remaining_time":5.545405315},
{"learn":[0.1268797179],"iteration":443,"passed_time":4.421193469,"remaining_time":5.536449479},
{"learn":[0.126686866],"iteration":444,"passed_time":4.431082467,"remaining_time":5.526406222},
{"learn":[0.1265362949],"iteration":445,"passed_time":4.441648928,"remaining_time":5.51720517},
{"learn":[0.1263002612],"iteration":446,"passed_time":4.453168356,"remaining_time":5.50917696},
{"learn":[0.1260868282],"iteration":447,"passed_time":4.462710842,"remaining_time":5.498697287},
{"learn":[0.1258903851],"iteration":448,"passed_time":4.472720094,"remaining_time":5.488794592},
{"learn":[0.1256091206],"iteration":449,"passed_time":4.484157163,"remaining_time":5.480636533},
{"learn":[0.1251846514],"iteration":450,"passed_time":4.493135362,"remaining_time":5.469470762},
{"learn":[0.1247818203],"iteration":451,"passed_time":4.502601276,"remaining_time":5.458905971},
{"learn":[0.1243915133],"iteration":452,"passed_time":4.512189761,"remaining_time":5.448494038},
{"learn":[0.1241469759],"iteration":453,"passed_time":4.521453858,"remaining_time":5.437695609},
{"learn":[0.1238541734],"iteration":454,"passed_time":4.532705628,"remaining_time":5.429284764},
{"learn":[0.1232383227],"iteration":455,"passed_time":4.541653692,"remaining_time":5.418113176},
{"learn":[0.1228008926],"iteration":456,"passed_time":4.551155219,"remaining_time":5.407608936},
{"learn":[0.1223593348],"iteration":457,"passed_time":4.566129057,"remaining_time":5.403585041},
{"learn":[0.1221989116],"iteration":458,"passed_time":4.575424304,"remaining_time":5.392820367},
{"learn":[0.12204616],"iteration":459,"passed_time":4.586453188,"remaining_time":5.384097221},
{"learn":[0.121811815],"iteration":460,"passed_time":4.597347923,"remaining_time":5.375207225},
{"learn":[0.1216278746],"iteration":461,"passed_time":4.605707689,"remaining_time":5.363356573},
{"learn":[0.1213479141],"iteration":462,"passed_time":4.61585285,"remaining_time":5.353591751},
{"learn":[0.1210296864],"iteration":463,"passed_time":4.62631951,"remaining_time":5.344196675},
{"learn":[0.120804493],"iteration":464,"passed_time":4.635772808,"remaining_time":5.33363108},
{"learn":[0.1203865181],"iteration":465,"passed_time":4.647331596,"remaining_time":5.325482987},
{"learn":[0.1202169546],"iteration":466,"passed_time":4.656029791,"remaining_time":5.314055414},
{"learn":[0.1201225021],"iteration":467,"passed_time":4.666191715,"remaining_time":5.304303403},
{"learn":[0.1199654046],"iteration":468,"passed_time":4.67520455,"remaining_time":5.293248649},
{"learn":[0.1198271645],"iteration":469,"passed_time":4.684394267,"remaining_time":5.282402046},
{"learn":[0.1195920319],"iteration":470,"passed_time":4.694893319,"remaining_time":5.273033048},
{"learn":[0.119242299],"iteration":471,"passed_time":4.703657919,"remaining_time":5.261719029},
{"learn":[0.1189554441],"iteration":472,"passed_time":4.713291443,"remaining_time":5.251383912},
{"learn":[0.1186909306],"iteration":473,"passed_time":4.722169754,"remaining_time":5.240213693},
{"learn":[0.1185243861],"iteration":474,"passed_time":4.731717103,"remaining_time":5.229792588},
{"learn":[0.1181908923],"iteration":475,"passed_time":4.741788957,"remaining_time":5.219952549},
{"learn":[0.1177559613],"iteration":476,"passed_time":4.750526609,"remaining_time":5.208648672},
{"learn":[0.1175126333],"iteration":477,"passed_time":4.759970649,"remaining_time":5.198126943},
{"learn":[0.1171744962],"iteration":478,"passed_time":4.768937544,"remaining_time":5.187090732},
{"learn":[0.1170178006],"iteration":479,"passed_time":4.777999787,"remaining_time":5.176166436},
{"learn":[0.1166168944],"iteration":480,"passed_time":4.787813222,"remaining_time":5.166060421},
{"learn":[0.1162736703],"iteration":481,"passed_time":4.797416014,"remaining_time":5.155729244},
{"learn":[0.1156847601],"iteration":482,"passed_time":4.808297104,"remaining_time":5.146769364},
{"learn":[0.1154697095],"iteration":483,"passed_time":4.817002817,"remaining_time":5.135482342},
{"learn":[0.1153123261],"iteration":484,"passed_time":4.826728341,"remaining_time":5.125288857},
{"learn":[0.1150590396],"iteration":485,"passed_time":4.836105461,"remaining_time":5.114728821},
{"learn":[0.11483778],"iteration":486,"passed_time":4.850015044,"remaining_time":5.108948086},
{"learn":[0.1146800349],"iteration":487,"passed_time":4.860106864,"remaining_time":5.099128513},
{"learn":[0.1144776298],"iteration":488,"passed_time":4.869373522,"remaining_time":5.088445541},
{"learn":[0.1143263836],"iteration":489,"passed_time":4.879328831,"remaining_time":5.07848511},
{"learn":[0.1141059329],"iteration":490,"passed_time":4.890752531,"remaining_time":5.070046921},
{"learn":[0.1138084927],"iteration":491,"passed_time":4.899643471,"remaining_time":5.05898147},
{"learn":[0.1133621535],"iteration":492,"passed_time":4.909206762,"remaining_time":5.048616284},
{"learn":[0.1129770892],"iteration":493,"passed_time":4.918909898,"remaining_time":5.038397588},
{"learn":[0.1125278592],"iteration":494,"passed_time":4.927765851,"remaining_time":5.027316677},
{"learn":[0.1123692552],"iteration":495,"passed_time":4.938724267,"remaining_time":5.01838111},
{"learn":[0.1120502732],"iteration":496,"passed_time":4.947893445,"remaining_time":5.007626565},
{"learn":[0.111872333],"iteration":497,"passed_time":4.957719734,"remaining_time":4.997540776},
{"learn":[0.1117197578],"iteration":498,"passed_time":4.967734947,"remaining_time":4.987645708},
{"learn":[0.111401062],"iteration":499,"passed_time":4.976147504,"remaining_time":4.976147504},
{"learn":[0.1110997902],"iteration":500,"passed_time":4.985626152,"remaining_time":4.965723453},
{"learn":[0.1109401341],"iteration":501,"passed_time":4.993511533,"remaining_time":4.953722597},
{"learn":[0.1106499906],"iteration":502,"passed_time":5.003705582,"remaining_time":4.944019233},
{"learn":[0.1104815673],"iteration":503,"passed_time":5.013978273,"remaining_time":4.934391316},
{"learn":[0.1103094257],"iteration":504,"passed_time":5.026227665,"remaining_time":4.926698404},
{"learn":[0.1101116942],"iteration":505,"passed_time":5.036989619,"remaining_time":4.91753532},
{"learn":[0.1098835866],"iteration":506,"passed_time":5.048166706,"remaining_time":4.908769598},
{"learn":[0.1097411745],"iteration":507,"passed_time":5.05732513,"remaining_time":4.898039299},
{"learn":[0.1093130204],"iteration":508,"passed_time":5.067820063,"remaining_time":4.888604423},
{"learn":[0.1091182087],"iteration":509,"passed_time":5.078060335,"remaining_time":4.878920714},
{"learn":[0.1088833173],"iteration":510,"passed_time":5.089691453,"remaining_time":4.870565794},
{"learn":[0.1087025661],"iteration":511,"passed_time":5.09974637,"remaining_time":4.860695759},
{"learn":[0.1082807108],"iteration":512,"passed_time":5.108863591,"remaining_time":4.849934832},
{"learn":[0.1080886481],"iteration":513,"passed_time":5.118430011,"remaining_time":4.83960503},
{"learn":[0.1078079715],"iteration":514,"passed_time":5.127212129,"remaining_time":4.828539578},
{"learn":[0.10764581],"iteration":515,"passed_time":5.137207919,"remaining_time":4.818621382},
{"learn":[0.107239367],"iteration":516,"passed_time":5.148359102,"remaining_time":4.809782294},
{"learn":[0.1071804293],"iteration":517,"passed_time":5.155582805,"remaining_time":4.797279753},
{"learn":[0.1070302337],"iteration":518,"passed_time":5.165579191,"remaining_time":4.787367227},
{"learn":[0.1066923892],"iteration":519,"passed_time":5.175196055,"remaining_time":4.77710405},
{"learn":[0.1064535859],"iteration":520,"passed_time":5.18455163,"remaining_time":4.76660313},
{"learn":[0.1062795958],"iteration":521,"passed_time":5.193164205,"remaining_time":4.755426226},
{"learn":[0.1059231156],"iteration":522,"passed_time":5.20248854,"remaining_time":4.744908286},
{"learn":[0.1057370024],"iteration":523,"passed_time":5.213493155,"remaining_time":4.735921263},
{"learn":[0.1055447796],"iteration":524,"passed_time":5.22325837,"remaining_time":4.725805192},
{"learn":[0.105328625],"iteration":525,"passed_time":5.234262347,"remaining_time":4.716806754},
{"learn":[0.1051931714],"iteration":526,"passed_time":5.248359086,"remaining_time":4.710576561},
{"learn":[0.1049619904],"iteration":527,"passed_time":5.258051477,"remaining_time":4.700379351},
{"learn":[0.1045909747],"iteration":528,"passed_time":5.267980048,"remaining_time":4.690394334},
{"learn":[0.1043656433],"iteration":529,"passed_time":5.279727931,"remaining_time":4.682022882},
{"learn":[0.1039918945],"iteration":530,"passed_time":5.291051559,"remaining_time":4.673263995},
{"learn":[0.1037036627],"iteration":531,"passed_time":5.299847581,"remaining_time":4.662271932},
{"learn":[0.1035420324],"iteration":532,"passed_time":5.310859064,"remaining_time":4.653229236},
{"learn":[0.1033815937],"iteration":533,"passed_time":5.320289085,"remaining_time":4.642799089},
{"learn":[0.1032158841],"iteration":534,"passed_time":5.329799306,"remaining_time":4.632442388},
{"learn":[0.1029405346],"iteration":535,"passed_time":5.339799235,"remaining_time":4.622512771},
{"learn":[0.1028169875],"iteration":536,"passed_time":5.349417635,"remaining_time":4.612253939},
{"learn":[0.1025879516],"iteration":537,"passed_time":5.359318019,"remaining_time":4.602239637},
{"learn":[0.1024423148],"iteration":538,"passed_time":5.367944051,"remaining_time":4.591135821},
{"learn":[0.1022626683],"iteration":539,"passed_time":5.377997251,"remaining_time":4.581256917},
{"learn":[0.1020541236],"iteration":540,"passed_time":5.387125452,"remaining_time":4.570592574},
{"learn":[0.1019020895],"iteration":541,"passed_time":5.39698073,"remaining_time":4.560548292},
{"learn":[0.1015212823],"iteration":542,"passed_time":5.40776128,"remaining_time":4.551283434},
{"learn":[0.1014392175],"iteration":543,"passed_time":5.415880475,"remaining_time":4.539782163},
{"learn":[0.1011969337],"iteration":544,"passed_time":5.426369811,"remaining_time":4.530272044},
{"learn":[0.1009817419],"iteration":545,"passed_time":5.435064532,"remaining_time":4.519266113},
{"learn":[0.1007936856],"iteration":546,"passed_time":5.44516267,"remaining_time":4.509430877},
{"learn":[0.1005647403],"iteration":547,"passed_time":5.454165027,"remaining_time":4.498690862},
{"learn":[0.1003406762],"iteration":548,"passed_time":5.463085639,"remaining_time":4.487890024},
{"learn":[0.100176592],"iteration":549,"passed_time":5.472404539,"remaining_time":4.477421895},
{"learn":[0.09997097788],"iteration":550,"passed_time":5.4798682,"remaining_time":4.465446138},
{"learn":[0.09979124892],"iteration":551,"passed_time":5.490640267,"remaining_time":4.456171811},
{"learn":[0.09951291071],"iteration":552,"passed_time":5.499936317,"remaining_time":4.445698976},
{"learn":[0.09928864836],"iteration":553,"passed_time":5.509839696,"remaining_time":4.435719322},
{"learn":[0.09898017287],"iteration":554,"passed_time":5.519855471,"remaining_time":4.425830062},
{"learn":[0.09880898134],"iteration":555,"passed_time":5.528572064,"remaining_time":4.414902871},
{"learn":[0.09867917265],"iteration":556,"passed_time":5.538941316,"remaining_time":4.405298031},
{"learn":[0.098585156],"iteration":557,"passed_time":5.548922688,"remaining_time":4.395383204},
{"learn":[0.09834800344],"iteration":558,"passed_time":5.561691904,"remaining_time":4.387667495},
{"learn":[0.09820111126],"iteration":559,"passed_time":5.571533527,"remaining_time":4.377633485},
{"learn":[0.09787124626],"iteration":560,"passed_time":5.580557522,"remaining_time":4.366960343},
{"learn":[0.09764461167],"iteration":561,"passed_time":5.590849471,"remaining_time":4.35728126},
{"learn":[0.09749302594],"iteration":562,"passed_time":5.599842202,"remaining_time":4.346591549},
{"learn":[0.09722680177],"iteration":563,"passed_time":5.60871738,"remaining_time":4.335816981},
{"learn":[0.09714506908],"iteration":564,"passed_time":5.618186923,"remaining_time":4.325506746},
{"learn":[0.09699223933],"iteration":565,"passed_time":5.626459384,"remaining_time":4.314281577},
{"learn":[0.09670253327],"iteration":566,"passed_time":5.636845043,"remaining_time":4.304680606},
{"learn":[0.0965811256],"iteration":567,"passed_time":5.64660349,"remaining_time":4.294599837},
{"learn":[0.09647213155],"iteration":568,"passed_time":5.656112979,"remaining_time":4.284331624},
{"learn":[0.0963250931],"iteration":569,"passed_time":5.665306608,"remaining_time":4.273827792},
{"learn":[0.09611586984],"iteration":570,"passed_time":5.673965397,"remaining_time":4.262926717},
{"learn":[0.09583053356],"iteration":571,"passed_time":5.684985276,"remaining_time":4.253800171},
{"learn":[0.09568548375],"iteration":572,"passed_time":5.693570085,"remaining_time":4.242852402},
{"learn":[0.09531372159],"iteration":573,"passed_time":5.703508983,"remaining_time":4.232917816},
{"learn":[0.09506372092],"iteration":574,"passed_time":5.712054834,"remaining_time":4.221953573},
{"learn":[0.09491195295],"iteration":575,"passed_time":5.722301985,"remaining_time":4.212250073},
{"learn":[0.09475947771],"iteration":576,"passed_time":5.733399342,"remaining_time":4.203167975},
{"learn":[0.09464467326],"iteration":577,"passed_time":5.741470903,"remaining_time":4.19186976},
{"learn":[0.09440081325],"iteration":578,"passed_time":5.752035201,"remaining_time":4.182395198},
{"learn":[0.09406581779],"iteration":579,"passed_time":5.760975905,"remaining_time":4.171741172},
{"learn":[0.09396976562],"iteration":580,"passed_time":5.769868608,"remaining_time":4.161058428},
{"learn":[0.09356970251],"iteration":581,"passed_time":5.77971676,"remaining_time":4.151068051},
{"learn":[0.09340368071],"iteration":582,"passed_time":5.789181625,"remaining_time":4.14080401},
{"learn":[0.09332890946],"iteration":583,"passed_time":5.799043998,"remaining_time":4.130825861},
{"learn":[0.09321700969],"iteration":584,"passed_time":5.807545004,"remaining_time":4.119882353},
{"learn":[0.09305473192],"iteration":585,"passed_time":5.817535367,"remaining_time":4.109999389},
{"learn":[0.09293976351],"iteration":586,"passed_time":5.82688218,"remaining_time":4.099663271},
{"learn":[0.09274460972],"iteration":587,"passed_time":5.836709441,"remaining_time":4.089667159},
{"learn":[0.09265818004],"iteration":588,"passed_time":5.846691289,"remaining_time":4.079779491},
{"learn":[0.09235207039],"iteration":589,"passed_time":5.855478838,"remaining_time":4.069061566},
{"learn":[0.09197810408],"iteration":590,"passed_time":5.864962251,"remaining_time":4.058831744},
{"learn":[0.09170337401],"iteration":591,"passed_time":5.873920761,"remaining_time":4.048242687},
{"learn":[0.09156633171],"iteration":592,"passed_time":5.883180674,"remaining_time":4.037865994},
{"learn":[0.09140679381],"iteration":593,"passed_time":5.892051676,"remaining_time":4.02722724},
{"learn":[0.09126580436],"iteration":594,"passed_time":5.900802943,"remaining_time":4.016512928},
{"learn":[0.09111484669],"iteration":595,"passed_time":5.912039352,"remaining_time":4.007489762},
{"learn":[0.09093070829],"iteration":596,"passed_time":5.921102155,"remaining_time":3.996991907},
{"learn":[0.09065358696],"iteration":597,"passed_time":5.931650614,"remaining_time":3.98749757},
{"learn":[0.0904154876],"iteration":598,"passed_time":5.940801498,"remaining_time":3.977064108},
{"learn":[0.09025024449],"iteration":599,"passed_time":5.949696137,"remaining_time":3.966464092},
{"learn":[0.09003003087],"iteration":600,"passed_time":5.959901087,"remaining_time":3.956739657},
{"learn":[0.0897655854],"iteration":601,"passed_time":5.968603372,"remaining_time":3.94602017},
{"learn":[0.08960394148],"iteration":602,"passed_time":5.978402981,"remaining_time":3.936029823},
{"learn":[0.08954337212],"iteration":603,"passed_time":5.9872558,"remaining_time":3.925419366},
{"learn":[0.08924803388],"iteration":604,"passed_time":5.998637806,"remaining_time":3.916466006},
{"learn":[0.08907731473],"iteration":605,"passed_time":6.009192402,"remaining_time":3.906966677},
{"learn":[0.08892912548],"iteration":606,"passed_time":6.017718888,"remaining_time":3.896150779},
{"learn":[0.08879719744],"iteration":607,"passed_time":6.027100888,"remaining_time":3.885893994},
{"learn":[0.08867859353],"iteration":608,"passed_time":6.036880396,"remaining_time":3.875895295},
{"learn":[0.08852570326],"iteration":609,"passed_time":6.051969564,"remaining_time":3.869292017},
{"learn":[0.08827580356],"iteration":610,"passed_time":6.063262164,"remaining_time":3.860243833},
{"learn":[0.08818902049],"iteration":611,"passed_time":6.072879697,"remaining_time":3.850126344},
{"learn":[0.08795057813],"iteration":612,"passed_time":6.081944326,"remaining_time":3.839661426},
{"learn":[0.08777342382],"iteration":613,"passed_time":6.091490717,"remaining_time":3.829503936},
{"learn":[0.0876134176],"iteration":614,"passed_time":6.099984735,"remaining_time":3.818689631},
{"learn":[0.08728569676],"iteration":615,"passed_time":6.11015381,"remaining_time":3.80892705},
{"learn":[0.08711261521],"iteration":616,"passed_time":6.119765583,"remaining_time":3.79881721},
{"learn":[0.08695495218],"iteration":617,"passed_time":6.129621319,"remaining_time":3.788859779},
{"learn":[0.08663027575],"iteration":618,"passed_time":6.139926023,"remaining_time":3.779179022},
{"learn":[0.08652530075],"iteration":619,"passed_time":6.14869342,"remaining_time":3.768554032},
{"learn":[0.08627192357],"iteration":620,"passed_time":6.158574439,"remaining_time":3.758614674},
{"learn":[0.08606578038],"iteration":621,"passed_time":6.168976762,"remaining_time":3.748992309},
{"learn":[0.08599316531],"iteration":622,"passed_time":6.178838194,"remaining_time":3.739040127},
{"learn":[0.08585549581],"iteration":623,"passed_time":6.188981995,"remaining_time":3.729258382},
{"learn":[0.08573266279],"iteration":624,"passed_time":6.197791457,"remaining_time":3.718674874},
{"learn":[0.08558862079],"iteration":625,"passed_time":6.207335655,"remaining_time":3.708535999},
{"learn":[0.08546064381],"iteration":626,"passed_time":6.215798043,"remaining_time":3.697755455},
{"learn":[0.08532727769],"iteration":627,"passed_time":6.22549913,"remaining_time":3.687716045},
{"learn":[0.08521653996],"iteration":628,"passed_time":6.235048863,"remaining_time":3.677588439},
{"learn":[0.08505123956],"iteration":629,"passed_time":6.243963194,"remaining_time":3.667089495},
{"learn":[0.08490955281],"iteration":630,"passed_time":6.255240432,"remaining_time":3.657977368},
{"learn":[0.0847316971],"iteration":631,"passed_time":6.264668654,"remaining_time":3.647781748},
{"learn":[0.084487311],"iteration":632,"passed_time":6.277382217,"remaining_time":3.639493323},
{"learn":[0.08441170323],"iteration":633,"passed_time":6.288031601,"remaining_time":3.629999316},
{"learn":[0.08427654362],"iteration":634,"passed_time":6.297912194,"remaining_time":3.620059765},
{"learn":[0.08401509199],"iteration":635,"passed_time":6.307319451,"remaining_time":3.609849497},
{"learn":[0.08382883808],"iteration":636,"passed_time":6.318694138,"remaining_time":3.600762908},
{"learn":[0.0836526843],"iteration":637,"passed_time":6.327157185,"remaining_time":3.590017086},
{"learn":[0.08353333455],"iteration":638,"passed_time":6.33762385,"remaining_time":3.580410344},
{"learn":[0.08339587892],"iteration":639,"passed_time":6.347157633,"remaining_time":3.570276169},
{"learn":[0.08322099648],"iteration":640,"passed_time":6.356222239,"remaining_time":3.559881098},
{"learn":[0.0830493301],"iteration":641,"passed_time":6.366710076,"remaining_time":3.550283812},
{"learn":[0.0828093745],"iteration":642,"passed_time":6.376736544,"remaining_time":3.540427599},
{"learn":[0.08268061438],"iteration":643,"passed_time":6.38634238,"remaining_time":3.530338334},
{"learn":[0.0825435662],"iteration":644,"passed_time":6.396139409,"remaining_time":3.520355799},
{"learn":[0.08235172667],"iteration":645,"passed_time":6.405893692,"remaining_time":3.510350413},
{"learn":[0.08224681781],"iteration":646,"passed_time":6.416072733,"remaining_time":3.50057755},
{"learn":[0.08215942239],"iteration":647,"passed_time":6.424550912,"remaining_time":3.489879508},
{"learn":[0.08197596205],"iteration":648,"passed_time":6.434037055,"remaining_time":3.479733446},
{"learn":[0.08176630494],"iteration":649,"passed_time":6.442328529,"remaining_time":3.468946131},
{"learn":[0.08164710529],"iteration":650,"passed_time":6.452806815,"remaining_time":3.45933883},
{"learn":[0.08146842841],"iteration":651,"passed_time":6.46299651,"remaining_time":3.449574824},
{"learn":[0.08137921579],"iteration":652,"passed_time":6.474200818,"remaining_time":3.440348674},
{"learn":[0.08131796546],"iteration":653,"passed_time":6.484592418,"remaining_time":3.430686508},
{"learn":[0.08123397603],"iteration":654,"passed_time":6.497763979,"remaining_time":3.422486371},
{"learn":[0.08118846153],"iteration":655,"passed_time":6.507919915,"remaining_time":3.412689711},
{"learn":[0.08100240501],"iteration":656,"passed_time":6.517836332,"remaining_time":3.402766913},
{"learn":[0.08080576831],"iteration":657,"passed_time":6.529221619,"remaining_time":3.393607589},
{"learn":[0.08068368682],"iteration":658,"passed_time":6.53730385,"remaining_time":3.382732341},
{"learn":[0.08057163274],"iteration":659,"passed_time":6.547083499,"remaining_time":3.372739985},
{"learn":[0.08033768836],"iteration":660,"passed_time":6.555657247,"remaining_time":3.362129814},
{"learn":[0.08018203063],"iteration":661,"passed_time":6.564821957,"remaining_time":3.351827525},
{"learn":[0.08003506448],"iteration":662,"passed_time":6.574186635,"remaining_time":3.341630311},
{"learn":[0.07972321485],"iteration":663,"passed_time":6.583504462,"remaining_time":3.331411897},
{"learn":[0.07955652847],"iteration":664,"passed_time":6.594219393,"remaining_time":3.321899995},
{"learn":[0.07939652678],"iteration":665,"passed_time":6.603531976,"remaining_time":3.311681201},
{"learn":[0.07930172233],"iteration":666,"passed_time":6.613952046,"remaining_time":3.302018038},
{"learn":[0.07905741759],"iteration":667,"passed_time":6.622969347,"remaining_time":3.291655424},
{"learn":[0.07894854354],"iteration":668,"passed_time":6.633024437,"remaining_time":3.281810297},
{"learn":[0.07875963596],"iteration":669,"passed_time":6.643420035,"remaining_time":3.272132256},
{"learn":[0.07860549668],"iteration":670,"passed_time":6.652024718,"remaining_time":3.261573967},
{"learn":[0.07847840985],"iteration":671,"passed_time":6.66162168,"remaining_time":3.25150582},
{"learn":[0.07825481415],"iteration":672,"passed_time":6.670254641,"remaining_time":3.24097068},
{"learn":[0.07813108323],"iteration":673,"passed_time":6.680191099,"remaining_time":3.231071659},
{"learn":[0.07795226877],"iteration":674,"passed_time":6.689743114,"remaining_time":3.220987425},
{"learn":[0.07783620307],"iteration":675,"passed_time":6.697139229,"remaining_time":3.209871465},
{"learn":[0.0777010804],"iteration":676,"passed_time":6.707332999,"remaining_time":3.200101269},
{"learn":[0.07762146607],"iteration":677,"passed_time":6.716288544,"remaining_time":3.189741757},
{"learn":[0.07751193518],"iteration":678,"passed_time":6.726421201,"remaining_time":3.179942865},
{"learn":[0.0773633795],"iteration":679,"passed_time":6.735284837,"remaining_time":3.169545806},
{"learn":[0.07722639149],"iteration":680,"passed_time":6.744794834,"remaining_time":3.159456023},
{"learn":[0.07704005517],"iteration":681,"passed_time":6.754233319,"remaining_time":3.149334597},
{"learn":[0.0768630355],"iteration":682,"passed_time":6.764231236,"remaining_time":3.139474819},
{"learn":[0.07676312264],"iteration":683,"passed_time":6.773809885,"remaining_time":3.129420941},
{"learn":[0.07663933515],"iteration":684,"passed_time":6.783188204,"remaining_time":3.119276327},
{"learn":[0.07646600319],"iteration":685,"passed_time":6.792921955,"remaining_time":3.109296638},
{"learn":[0.07634959702],"iteration":686,"passed_time":6.802894692,"remaining_time":3.099426548},
{"learn":[0.0762025367],"iteration":687,"passed_time":6.811464197,"remaining_time":3.08891981},
{"learn":[0.07606022096],"iteration":688,"passed_time":6.822642484,"remaining_time":3.079596245},
{"learn":[0.07593422125],"iteration":689,"passed_time":6.832064889,"remaining_time":3.069478428},
{"learn":[0.07578487242],"iteration":690,"passed_time":6.841482127,"remaining_time":3.059360314},
{"learn":[0.0756757612],"iteration":691,"passed_time":6.851116684,"remaining_time":3.049340952},
{"learn":[0.07560898784],"iteration":692,"passed_time":6.859733982,"remaining_time":3.038872053},
{"learn":[0.07550690993],"iteration":693,"passed_time":6.870244921,"remaining_time":3.029243438},
{"learn":[0.07541091466],"iteration":694,"passed_time":6.878967186,"remaining_time":3.018827326},
{"learn":[0.0753653027],"iteration":695,"passed_time":6.888822396,"remaining_time":3.008910931},
{"learn":[0.07517343001],"iteration":696,"passed_time":6.897159608,"remaining_time":2.998334808},
{"learn":[0.0750193853],"iteration":697,"passed_time":6.907195866,"remaining_time":2.988500217},
{"learn":[0.07486300665],"iteration":698,"passed_time":6.916164962,"remaining_time":2.978205513},
{"learn":[0.07470648193],"iteration":699,"passed_time":6.925252064,"remaining_time":2.96796517},
{"learn":[0.07456951892],"iteration":700,"passed_time":6.935391753,"remaining_time":2.958177082},
{"learn":[0.07444806542],"iteration":701,"passed_time":6.943350391,"remaining_time":2.947462132},
{"learn":[0.07438472342],"iteration":702,"passed_time":6.954073468,"remaining_time":2.93792293},
{"learn":[0.07426318331],"iteration":703,"passed_time":6.961980663,"remaining_time":2.927196415},
{"learn":[0.07418274399],"iteration":704,"passed_time":6.973002479,"remaining_time":2.917781179},
{"learn":[0.07409095923],"iteration":705,"passed_time":6.982945808,"remaining_time":2.907912277},
{"learn":[0.07398382314],"iteration":706,"passed_time":6.990802567,"remaining_time":2.897178433},
{"learn":[0.07378249456],"iteration":707,"passed_time":7.001515666,"remaining_time":2.887630755},
{"learn":[0.07369280314],"iteration":708,"passed_time":7.010813321,"remaining_time":2.877498838},
{"learn":[0.07357441664],"iteration":709,"passed_time":7.020587288,"remaining_time":2.867563822},
{"learn":[0.0734508441],"iteration":710,"passed_time":7.030338921,"remaining_time":2.85762018},
{"learn":[0.0732217505],"iteration":711,"passed_time":7.039516734,"remaining_time":2.847444971},
{"learn":[0.07306980745],"iteration":712,"passed_time":7.050974437,"remaining_time":2.838190271},
{"learn":[0.07295247191],"iteration":713,"passed_time":7.062092223,"remaining_time":2.828793243},
{"learn":[0.07283689217],"iteration":714,"passed_time":7.071287454,"remaining_time":2.818625069},
{"learn":[0.07270400919],"iteration":715,"passed_time":7.081119448,"remaining_time":2.808712183},
{"learn":[0.07243106633],"iteration":716,"passed_time":7.089688426,"remaining_time":2.798301011},
{"learn":[0.07229752573],"iteration":717,"passed_time":7.099321824,"remaining_time":2.788313028},
{"learn":[0.07216993493],"iteration":718,"passed_time":7.108933472,"remaining_time":2.778317532},
{"learn":[0.07206869574],"iteration":719,"passed_time":7.118800215,"remaining_time":2.768422306},
{"learn":[0.07199086608],"iteration":720,"passed_time":7.128491646,"remaining_time":2.758459319},
{"learn":[0.07190444398],"iteration":721,"passed_time":7.138821964,"remaining_time":2.748743083},
{"learn":[0.07181501484],"iteration":722,"passed_time":7.149320218,"remaining_time":2.739089489},
{"learn":[0.07163942399],"iteration":723,"passed_time":7.158515721,"remaining_time":2.728936932},
{"learn":[0.07146601896],"iteration":724,"passed_time":7.167949421,"remaining_time":2.718877366},
{"learn":[0.07134213071],"iteration":725,"passed_time":7.178117975,"remaining_time":2.709096867},
{"learn":[0.0711792037],"iteration":726,"passed_time":7.186011108,"remaining_time":2.698460842},
{"learn":[0.0711006905],"iteration":727,"passed_time":7.196333295,"remaining_time":2.688739912},
{"learn":[0.07100929815],"iteration":728,"passed_time":7.205279035,"remaining_time":2.67850565},
{"learn":[0.07096791286],"iteration":729,"passed_time":7.215127016,"remaining_time":2.668608622},
{"learn":[0.07086056779],"iteration":730,"passed_time":7.223936026,"remaining_time":2.658329399},
{"learn":[0.07074879687],"iteration":731,"passed_time":7.232606169,"remaining_time":2.648003351},
{"learn":[0.07066837751],"iteration":732,"passed_time":7.243363886,"remaining_time":2.638442234},
{"learn":[0.07051948181],"iteration":733,"passed_time":7.251583665,"remaining_time":2.627958113},
{"learn":[0.07037009661],"iteration":734,"passed_time":7.262107785,"remaining_time":2.61831097},
{"learn":[0.0702301878],"iteration":735,"passed_time":7.271649316,"remaining_time":2.608308994},
{"learn":[0.07001248783],"iteration":736,"passed_time":7.281079694,"remaining_time":2.598268602},
{"learn":[0.06992938856],"iteration":737,"passed_time":7.290685194,"remaining_time":2.588292034},
{"learn":[0.06978639512],"iteration":738,"passed_time":7.298766337,"remaining_time":2.577778097},
{"learn":[0.06970712777],"iteration":739,"passed_time":7.308715836,"remaining_time":2.567927185},
{"learn":[0.06964303952],"iteration":740,"passed_time":7.317039547,"remaining_time":2.55750775},
{"learn":[0.06954103023],"iteration":741,"passed_time":7.327084207,"remaining_time":2.547692352},
{"learn":[0.06939775987],"iteration":742,"passed_time":7.336345191,"remaining_time":2.537605268},
{"learn":[0.06922083691],"iteration":743,"passed_time":7.346733731,"remaining_time":2.52790838},
{"learn":[0.06908918883],"iteration":744,"passed_time":7.356206291,"remaining_time":2.517896113},
{"learn":[0.06896274864],"iteration":745,"passed_time":7.364598571,"remaining_time":2.507517476},
{"learn":[0.06884802875],"iteration":746,"passed_time":7.374207703,"remaining_time":2.49755629},
{"learn":[0.06874888177],"iteration":747,"passed_time":7.3825182,"remaining_time":2.487158538},
{"learn":[0.06847075444],"iteration":748,"passed_time":7.392243671,"remaining_time":2.477240536},
{"learn":[0.06838796595],"iteration":749,"passed_time":7.40091859,"remaining_time":2.466972863},
{"learn":[0.06826603203],"iteration":750,"passed_time":7.411014675,"remaining_time":2.457180631},
{"learn":[0.06817383051],"iteration":751,"passed_time":7.421754292,"remaining_time":2.44759982},
{"learn":[0.06802469842],"iteration":752,"passed_time":7.43052501,"remaining_time":2.43737009},
{"learn":[0.06792574539],"iteration":753,"passed_time":7.439912749,"remaining_time":2.427345539},
{"learn":[0.06783035114],"iteration":754,"passed_time":7.447925538,"remaining_time":2.416876499},
{"learn":[0.06767964374],"iteration":755,"passed_time":7.457752849,"remaining_time":2.406999597},
{"learn":[0.06754871684],"iteration":756,"passed_time":7.466900047,"remaining_time":2.396904506},
{"learn":[0.06745831294],"iteration":757,"passed_time":7.476303874,"remaining_time":2.386893849},
{"learn":[0.06725627812],"iteration":758,"passed_time":7.487687239,"remaining_time":2.37751334},
{"learn":[0.06715432932],"iteration":759,"passed_time":7.498509387,"remaining_time":2.367950333},
{"learn":[0.06706070044],"iteration":760,"passed_time":7.509042248,"remaining_time":2.358293163},
{"learn":[0.06697405092],"iteration":761,"passed_time":7.519563599,"remaining_time":2.348630101},
{"learn":[0.06691291809],"iteration":762,"passed_time":7.52827423,"remaining_time":2.338402349},
{"learn":[0.06679050849],"iteration":763,"passed_time":7.537860734,"remaining_time":2.328449127},
{"learn":[0.06667209555],"iteration":764,"passed_time":7.54713131,"remaining_time":2.318399814},
{"learn":[0.06655055367],"iteration":765,"passed_time":7.556145617,"remaining_time":2.308274249},
{"learn":[0.0664602926],"iteration":766,"passed_time":7.565078289,"remaining_time":2.298126781},
{"learn":[0.06640561301],"iteration":767,"passed_time":7.574638703,"remaining_time":2.288172108},
{"learn":[0.06631096772],"iteration":768,"passed_time":7.58574302,"remaining_time":2.278682234},
{"learn":[0.06622535695],"iteration":769,"passed_time":7.595018469,"remaining_time":2.26864188},
{"learn":[0.06613310283],"iteration":770,"passed_time":7.604464956,"remaining_time":2.258654313},
{"learn":[0.06598890349],"iteration":771,"passed_time":7.613890811,"remaining_time":2.248662053},
{"learn":[0.06588296136],"iteration":772,"passed_time":7.62313526,"remaining_time":2.238617987},
{"learn":[0.06574013566],"iteration":773,"passed_time":7.634180384,"remaining_time":2.229101766},
{"learn":[0.06560225259],"iteration":774,"passed_time":7.64408501,"remaining_time":2.219250487},
{"learn":[0.0655529175],"iteration":775,"passed_time":7.653678964,"remaining_time":2.209309392},
{"learn":[0.0654135496],"iteration":776,"passed_time":7.662441774,"remaining_time":2.199130651},
{"learn":[0.06528565316],"iteration":777,"passed_time":7.67200246,"remaining_time":2.189183221},
{"learn":[0.0651445373],"iteration":778,"passed_time":7.681310465,"remaining_time":2.1791651},
{"learn":[0.06506140351],"iteration":779,"passed_time":7.690847291,"remaining_time":2.169213338},
{"learn":[0.06498497894],"iteration":780,"passed_time":7.700537371,"remaining_time":2.159305614},
{"learn":[0.06488711087],"iteration":781,"passed_time":7.70928219,"remaining_time":2.149134933},
{"learn":[0.0647971821],"iteration":782,"passed_time":7.718993314,"remaining_time":2.139235695},
{"learn":[0.0645703383],"iteration":783,"passed_time":7.727715023,"remaining_time":2.129064343},
{"learn":[0.06440036595],"iteration":784,"passed_time":7.737925707,"remaining_time":2.119304493},
{"learn":[0.06420356071],"iteration":785,"passed_time":7.749064725,"remaining_time":2.109796248},
{"learn":[0.06408669177],"iteration":786,"passed_time":7.757503271,"remaining_time":2.099552982},
{"learn":[0.06393743455],"iteration":787,"passed_time":7.768731057,"remaining_time":2.090064701},
{"learn":[0.06379587928],"iteration":788,"passed_time":7.779492827,"remaining_time":2.080447385},
{"learn":[0.06370936598],"iteration":789,"passed_time":7.790224681,"remaining_time":2.070819219},
{"learn":[0.06365993209],"iteration":790,"passed_time":7.800425211,"remaining_time":2.061047875},
{"learn":[0.06359414904],"iteration":791,"passed_time":7.808709815,"remaining_time":2.050772275},
{"learn":[0.06348591089],"iteration":792,"passed_time":7.81852404,"remaining_time":2.040900979},
{"learn":[0.06330652801],"iteration":793,"passed_time":7.828630957,"remaining_time":2.031105765},
{"learn":[0.06319106102],"iteration":794,"passed_time":7.836869545,"remaining_time":2.020827996},
{"learn":[0.06312254557],"iteration":795,"passed_time":7.846822515,"remaining_time":2.010994715},
{"learn":[0.06300947054],"iteration":796,"passed_time":7.856609008,"remaining_time":2.001118731},
{"learn":[0.06292780872],"iteration":797,"passed_time":7.865888323,"remaining_time":1.991114588},
{"learn":[0.0628736648],"iteration":798,"passed_time":7.875453497,"remaining_time":1.981184171},
{"learn":[0.06278702436],"iteration":799,"passed_time":7.884130258,"remaining_time":1.971032564},
{"learn":[0.06268943599],"iteration":800,"passed_time":7.895169789,"remaining_time":1.961471645},
{"learn":[0.06255905955],"iteration":801,"passed_time":7.903967327,"remaining_time":1.95135353},
{"learn":[0.06239839315],"iteration":802,"passed_time":7.913903992,"remaining_time":1.941518165},
{"learn":[0.06234658796],"iteration":803,"passed_time":7.92320763,"remaining_time":1.931528228},
{"learn":[0.06223759363],"iteration":804,"passed_time":7.933467404,"remaining_time":1.921771607},
{"learn":[0.06206036149],"iteration":805,"passed_time":7.945172552,"remaining_time":1.912361632},
{"learn":[0.06194228461],"iteration":806,"passed_time":7.954561643,"remaining_time":1.902392066},
{"learn":[0.06184702444],"iteration":807,"passed_time":7.964711675,"remaining_time":1.892604754},
{"learn":[0.06171764018],"iteration":808,"passed_time":7.974208957,"remaining_time":1.882662436},
{"learn":[0.06158155376],"iteration":809,"passed_time":7.985229139,"remaining_time":1.87307844},
{"learn":[0.06154191822],"iteration":810,"passed_time":7.995871012,"remaining_time":1.863402739},
{"learn":[0.06146954828],"iteration":811,"passed_time":8.00691196,"remaining_time":1.853817055},
{"learn":[0.06135084431],"iteration":812,"passed_time":8.015937135,"remaining_time":1.843764138},
{"learn":[0.06125470666],"iteration":813,"passed_time":8.026031533,"remaining_time":1.833958065},
{"learn":[0.06119889358],"iteration":814,"passed_time":8.035172856,"remaining_time":1.823934943},
{"learn":[0.06109301126],"iteration":815,"passed_time":8.04596694,"remaining_time":1.814286663},
{"learn":[0.06099922405],"iteration":816,"passed_time":8.057407389,"remaining_time":1.804780358},
{"learn":[0.06088423886],"iteration":817,"passed_time":8.065963545,"remaining_time":1.794627586},
{"learn":[0.06082133612],"iteration":818,"passed_time":8.075347688,"remaining_time":1.784661699},
{"learn":[0.06075613198],"iteration":819,"passed_time":8.08564236,"remaining_time":1.774897103},
{"learn":[0.06062506672],"iteration":820,"passed_time":8.093954553,"remaining_time":1.764698983},
{"learn":[0.06056781008],"iteration":821,"passed_time":8.104490762,"remaining_time":1.754987051},
{"learn":[0.06045695411],"iteration":822,"passed_time":8.113486576,"remaining_time":1.744941827},
{"learn":[0.06036323157],"iteration":823,"passed_time":8.123779106,"remaining_time":1.73517612},
{"learn":[0.06028059594],"iteration":824,"passed_time":8.133617646,"remaining_time":1.725312834},
{"learn":[0.06019418695],"iteration":825,"passed_time":8.145123718,"remaining_time":1.71580088},
{"learn":[0.06013444319],"iteration":826,"passed_time":8.155052638,"remaining_time":1.705954179},
{"learn":[0.05995067303],"iteration":827,"passed_time":8.165271253,"remaining_time":1.696167458},
{"learn":[0.05984538786],"iteration":828,"passed_time":8.174397903,"remaining_time":1.686154453},
{"learn":[0.05968101634],"iteration":829,"passed_time":8.183491974,"remaining_time":1.67613691},
{"learn":[0.05958684923],"iteration":830,"passed_time":8.19225951,"remaining_time":1.666055183},
{"learn":[0.05951753873],"iteration":831,"passed_time":8.203290323,"remaining_time":1.656433623},
{"learn":[0.05938125191],"iteration":832,"passed_time":8.211976422,"remaining_time":1.64633861},
{"learn":[0.05925726313],"iteration":833,"passed_time":8.221662884,"remaining_time":1.63644609},
{"learn":[0.05912908404],"iteration":834,"passed_time":8.231188851,"remaining_time":1.626522348},
{"learn":[0.05900374926],"iteration":835,"passed_time":8.241086615,"remaining_time":1.616672494},
{"learn":[0.05886070468],"iteration":836,"passed_time":8.25231196,"remaining_time":1.607081063},
{"learn":[0.05881630412],"iteration":837,"passed_time":8.261514883,"remaining_time":1.597094763},
{"learn":[0.05870325211],"iteration":838,"passed_time":8.271698698,"remaining_time":1.587298558},
{"learn":[0.0586204067],"iteration":839,"passed_time":8.280585098,"remaining_time":1.577254304},
{"learn":[0.05852225809],"iteration":840,"passed_time":8.289389073,"remaining_time":1.567197221},
{"learn":[0.05839819518],"iteration":841,"passed_time":8.298274167,"remaining_time":1.557158335},
{"learn":[0.05833223213],"iteration":842,"passed_time":8.306285216,"remaining_time":1.546959406},
{"learn":[0.05824166107],"iteration":843,"passed_time":8.316730081,"remaining_time":1.537215513},
{"learn":[0.05809111667],"iteration":844,"passed_time":8.32562136,"remaining_time":1.527184983},
{"learn":[0.05795722692],"iteration":845,"passed_time":8.334849829,"remaining_time":1.517218527},
{"learn":[0.05778126035],"iteration":846,"passed_time":8.344993655,"remaining_time":1.507419161},
{"learn":[0.05769695077],"iteration":847,"passed_time":8.35376164,"remaining_time":1.49737237},
{"learn":[0.05757818397],"iteration":848,"passed_time":8.364312376,"remaining_time":1.487645664},
{"learn":[0.05748693825],"iteration":849,"passed_time":8.378084352,"remaining_time":1.478485474},
{"learn":[0.05741204078],"iteration":850,"passed_time":8.386762898,"remaining_time":1.468422646},
{"learn":[0.05735296905],"iteration":851,"passed_time":8.396973451,"remaining_time":1.458629191},
{"learn":[0.05727522253],"iteration":852,"passed_time":8.405552804,"remaining_time":1.448553649},
{"learn":[0.05709524662],"iteration":853,"passed_time":8.415287127,"remaining_time":1.438679064},
{"learn":[0.05695307877],"iteration":854,"passed_time":8.423848975,"remaining_time":1.428605967},
{"learn":[0.05685314721],"iteration":855,"passed_time":8.433720461,"remaining_time":1.418756713},
{"learn":[0.05678138523],"iteration":856,"passed_time":8.443278264,"remaining_time":1.408855066},
{"learn":[0.05667782985],"iteration":857,"passed_time":8.454078694,"remaining_time":1.399159877},
{"learn":[0.05660074631],"iteration":858,"passed_time":8.464409851,"remaining_time":1.389385086},
{"learn":[0.05655702264],"iteration":859,"passed_time":8.473471749,"remaining_time":1.379402378},
{"learn":[0.0564627356],"iteration":860,"passed_time":8.483374018,"remaining_time":1.369557478},
{"learn":[0.05638879484],"iteration":861,"passed_time":8.49289213,"remaining_time":1.359650944},
{"learn":[0.05630240927],"iteration":862,"passed_time":8.50291432,"remaining_time":1.349825332},
{"learn":[0.0562139644],"iteration":863,"passed_time":8.513410739,"remaining_time":1.340073913},
{"learn":[0.05603174188],"iteration":864,"passed_time":8.522274476,"remaining_time":1.330065959},
{"learn":[0.0559766901],"iteration":865,"passed_time":8.532387368,"remaining_time":1.320253935},
{"learn":[0.05586823021],"iteration":866,"passed_time":8.542942706,"remaining_time":1.310509089},
{"learn":[0.05579639495],"iteration":867,"passed_time":8.552328356,"remaining_time":1.300584497},
{"learn":[0.05573734141],"iteration":868,"passed_time":8.562186075,"remaining_time":1.290732308},
{"learn":[0.05567234741],"iteration":869,"passed_time":8.572664437,"remaining_time":1.280972847},
{"learn":[0.05560382337],"iteration":870,"passed_time":8.581124945,"remaining_time":1.270912879},
{"learn":[0.05552284111],"iteration":871,"passed_time":8.593621981,"remaining_time":1.261449098},
{"learn":[0.05538983518],"iteration":872,"passed_time":8.60308637,"remaining_time":1.251537192},
{"learn":[0.05532434057],"iteration":873,"passed_time":8.612282879,"remaining_time":1.241587692},
{"learn":[0.05527308222],"iteration":874,"passed_time":8.621324247,"remaining_time":1.23161775},
{"learn":[0.05519871221],"iteration":875,"passed_time":8.63060353,"remaining_time":1.221683605},
{"learn":[0.05507732162],"iteration":876,"passed_time":8.63993072,"remaining_time":1.211757672},
{"learn":[0.0550031408],"iteration":877,"passed_time":8.648658156,"remaining_time":1.201749767},
{"learn":[0.05486777622],"iteration":878,"passed_time":8.658165574,"remaining_time":1.191852144},
{"learn":[0.05477902861],"iteration":879,"passed_time":8.66722088,"remaining_time":1.181893756},
{"learn":[0.05466199019],"iteration":880,"passed_time":8.67687298,"remaining_time":1.17201803},
{"learn":[0.0545519883],"iteration":881,"passed_time":8.685372912,"remaining_time":1.161988666},
{"learn":[0.05446751126],"iteration":882,"passed_time":8.695193448,"remaining_time":1.15213775},
{"learn":[0.05441508095],"iteration":883,"passed_time":8.703921192,"remaining_time":1.142143505},
{"learn":[0.05434703816],"iteration":884,"passed_time":8.713359957,"remaining_time":1.132244514},
{"learn":[0.05429518268],"iteration":885,"passed_time":8.723343645,"remaining_time":1.122416677},
{"learn":[0.05424531185],"iteration":886,"passed_time":8.731666839,"remaining_time":1.112376948},
{"learn":[0.05415211706],"iteration":887,"passed_time":8.742189462,"remaining_time":1.102618491},
{"learn":[0.05407570995],"iteration":888,"passed_time":8.751387375,"remaining_time":1.092692912},
{"learn":[0.05400413522],"iteration":889,"passed_time":8.760477298,"remaining_time":1.082755621},
{"learn":[0.05394356347],"iteration":890,"passed_time":8.770792357,"remaining_time":1.072970109},
{"learn":[0.05382353042],"iteration":891,"passed_time":8.779272844,"remaining_time":1.062961286},
{"learn":[0.0537717663],"iteration":892,"passed_time":8.78928606,"remaining_time":1.053139539},
{"learn":[0.05366834998],"iteration":893,"passed_time":8.797860572,"remaining_time":1.043146779},
{"learn":[0.05357975123],"iteration":894,"passed_time":8.806857531,"remaining_time":1.033206749},
{"learn":[0.05344028467],"iteration":895,"passed_time":8.816304243,"remaining_time":1.023321028},
{"learn":[0.0533949247],"iteration":896,"passed_time":8.826514208,"remaining_time":1.013523928},
{"learn":[0.05332803879],"iteration":897,"passed_time":8.83667279,"remaining_time":1.003720072},
{"learn":[0.05320930064],"iteration":898,"passed_time":8.846211132,"remaining_time":0.9938457446},
{"learn":[0.05313303787],"iteration":899,"passed_time":8.855920841,"remaining_time":0.9839912046},
{"learn":[0.05304231978],"iteration":900,"passed_time":8.865495127,"remaining_time":0.9741221061},
{"learn":[0.05298891702],"iteration":901,"passed_time":8.8748054,"remaining_time":0.9642249769},
{"learn":[0.05294272188],"iteration":902,"passed_time":8.884975514,"remaining_time":0.9544215114},
{"learn":[0.0528889867],"iteration":903,"passed_time":8.89364396,"remaining_time":0.9444577657},
{"learn":[0.05281166795],"iteration":904,"passed_time":8.904437266,"remaining_time":0.934719934},
{"learn":[0.05272911505],"iteration":905,"passed_time":8.913268172,"remaining_time":0.9247761679},
{"learn":[0.05268017624],"iteration":906,"passed_time":8.923433201,"remaining_time":0.9149716513},
{"learn":[0.05262176842],"iteration":907,"passed_time":8.933646208,"remaining_time":0.9051712017},
{"learn":[0.05254560249],"iteration":908,"passed_time":8.941886285,"remaining_time":0.8951723343},
{"learn":[0.05245958449],"iteration":909,"passed_time":8.951835296,"remaining_time":0.885346348},
{"learn":[0.05240938397],"iteration":910,"passed_time":8.960204064,"remaining_time":0.8753657099},
{"learn":[0.0523381229],"iteration":911,"passed_time":8.970091924,"remaining_time":0.8655351857},
{"learn":[0.05228585576],"iteration":912,"passed_time":8.979389258,"remaining_time":0.8556482645},
{"learn":[0.05215259686],"iteration":913,"passed_time":8.989367744,"remaining_time":0.8458267243},
{"learn":[0.05202863096],"iteration":914,"passed_time":8.999201096,"remaining_time":0.8359913586},
{"learn":[0.05193497967],"iteration":915,"passed_time":9.007457869,"remaining_time":0.8260114203},
{"learn":[0.05189250606],"iteration":916,"passed_time":9.017498225,"remaining_time":0.8161966769},
{"learn":[0.05186013314],"iteration":917,"passed_time":9.025885747,"remaining_time":0.8062338031},
{"learn":[0.05180262165],"iteration":918,"passed_time":9.035267729,"remaining_time":0.7963620087},
{"learn":[0.05176698894],"iteration":919,"passed_time":9.045342947,"remaining_time":0.7865515606},
{"learn":[0.05171885605],"iteration":920,"passed_time":9.055678779,"remaining_time":0.776762892},
{"learn":[0.05167515937],"iteration":921,"passed_time":9.065376614,"remaining_time":0.7669190628},
{"learn":[0.05154599847],"iteration":922,"passed_time":9.07417215,"remaining_time":0.7570002768},
{"learn":[0.05148917932],"iteration":923,"passed_time":9.083588323,"remaining_time":0.7471349703},
{"learn":[0.05135658523],"iteration":924,"passed_time":9.092784598,"remaining_time":0.7372528052},
{"learn":[0.05130882459],"iteration":925,"passed_time":9.103726858,"remaining_time":0.7275116495},
{"learn":[0.05125500282],"iteration":926,"passed_time":9.113881821,"remaining_time":0.717705904},
{"learn":[0.05120608161],"iteration":927,"passed_time":9.122174285,"remaining_time":0.7077549015},
{"learn":[0.05103468385],"iteration":928,"passed_time":9.132182068,"remaining_time":0.697938565},
{"learn":[0.05095906512],"iteration":929,"passed_time":9.141281178,"remaining_time":0.688053422},
{"learn":[0.05090551313],"iteration":930,"passed_time":9.15120492,"remaining_time":0.6782310843},
{"learn":[0.05078900981],"iteration":931,"passed_time":9.161051817,"remaining_time":0.6684029222},
{"learn":[0.05070737444],"iteration":932,"passed_time":9.16874057,"remaining_time":0.6584197409},
{"learn":[0.05062179206],"iteration":933,"passed_time":9.179472615,"remaining_time":0.6486565231},
{"learn":[0.05054487139],"iteration":934,"passed_time":9.188490805,"remaining_time":0.638772088},
{"learn":[0.05042447063],"iteration":935,"passed_time":9.197925535,"remaining_time":0.6289179853},
{"learn":[0.05038695163],"iteration":936,"passed_time":9.207402258,"remaining_time":0.6190676012},
{"learn":[0.05028626051],"iteration":937,"passed_time":9.216000711,"remaining_time":0.6091599617},
{"learn":[0.05020625508],"iteration":938,"passed_time":9.225718733,"remaining_time":0.599327841},
{"learn":[0.05013513259],"iteration":939,"passed_time":9.233957413,"remaining_time":0.589401537},
{"learn":[0.05007987354],"iteration":940,"passed_time":9.244106594,"remaining_time":0.5795986069},
{"learn":[0.05004444141],"iteration":941,"passed_time":9.25301161,"remaining_time":0.5697183369},
{"learn":[0.04996348654],"iteration":942,"passed_time":9.262409575,"remaining_time":0.5598699319},
{"learn":[0.04989091934],"iteration":943,"passed_time":9.271509362,"remaining_time":0.5500047927},
{"learn":[0.04974414932],"iteration":944,"passed_time":9.280354832,"remaining_time":0.5401264717},
{"learn":[0.04967436417],"iteration":945,"passed_time":9.290853918,"remaining_time":0.5303447268},
{"learn":[0.04961329571],"iteration":946,"passed_time":9.2993215,"remaining_time":0.5204477714},
{"learn":[0.04955950515],"iteration":947,"passed_time":9.310128283,"remaining_time":0.5106821421},
{"learn":[0.04942847713],"iteration":948,"passed_time":9.320027124,"remaining_time":0.5008655251},
{"learn":[0.04936675572],"iteration":949,"passed_time":9.329368157,"remaining_time":0.4910193767},
{"learn":[0.04930589066],"iteration":950,"passed_time":9.338034076,"remaining_time":0.4811395055},
{"learn":[0.04925707363],"iteration":951,"passed_time":9.346815864,"remaining_time":0.4712680268},
{"learn":[0.04916714468],"iteration":952,"passed_time":9.357365753,"remaining_time":0.461486034},
{"learn":[0.04912710529],"iteration":953,"passed_time":9.366239753,"remaining_time":0.4516216233},
{"learn":[0.04906407352],"iteration":954,"passed_time":9.375861601,"remaining_time":0.4417945257},
{"learn":[0.04902384811],"iteration":955,"passed_time":9.385305158,"remaining_time":0.4319596516},
{"learn":[0.04897628268],"iteration":956,"passed_time":9.397446194,"remaining_time":0.4222467987},
{"learn":[0.04892260384],"iteration":957,"passed_time":9.408326988,"remaining_time":0.4124736258},
{"learn":[0.0488647728],"iteration":958,"passed_time":9.418165402,"remaining_time":0.4026535782},
{"learn":[0.04878684182],"iteration":959,"passed_time":9.429310632,"remaining_time":0.392887943},
{"learn":[0.04874030188],"iteration":960,"passed_time":9.439937344,"remaining_time":0.3830983938},
{"learn":[0.04868059722],"iteration":961,"passed_time":9.450040046,"remaining_time":0.3732864052},
{"learn":[0.04862715724],"iteration":962,"passed_time":9.460299507,"remaining_time":0.3634798357},
{"learn":[0.04860117248],"iteration":963,"passed_time":9.471936611,"remaining_time":0.3537237739},
{"learn":[0.04853651546],"iteration":964,"passed_time":9.481772634,"remaining_time":0.3438984893},
{"learn":[0.04848137224],"iteration":965,"passed_time":9.491409942,"remaining_time":0.3340661884},
{"learn":[0.0483796707],"iteration":966,"passed_time":9.503866907,"remaining_time":0.3243305149},
{"learn":[0.0482754159],"iteration":967,"passed_time":9.514064819,"remaining_time":0.3145145395},
{"learn":[0.04818594481],"iteration":968,"passed_time":9.525379875,"remaining_time":0.3047335151},
{"learn":[0.04812353138],"iteration":969,"passed_time":9.537447061,"remaining_time":0.2949725895},
{"learn":[0.04808876661],"iteration":970,"passed_time":9.545605732,"remaining_time":0.2850901815},
{"learn":[0.04801974142],"iteration":971,"passed_time":9.554837,"remaining_time":0.2752422181},
{"learn":[0.04799613529],"iteration":972,"passed_time":9.563612378,"remaining_time":0.2653828717},
{"learn":[0.04792543904],"iteration":973,"passed_time":9.573127932,"remaining_time":0.2555455095},
{"learn":[0.04780089401],"iteration":974,"passed_time":9.583953314,"remaining_time":0.2457423927},
{"learn":[0.04775875757],"iteration":975,"passed_time":9.592303862,"remaining_time":0.2358763245},
{"learn":[0.04769650204],"iteration":976,"passed_time":9.601749215,"remaining_time":0.226039132},
{"learn":[0.04765993132],"iteration":977,"passed_time":9.610205124,"remaining_time":0.2161804834},
{"learn":[0.04758845563],"iteration":978,"passed_time":9.61994278,"remaining_time":0.2063521945},
{"learn":[0.04752272266],"iteration":979,"passed_time":9.628868776,"remaining_time":0.196507526},
{"learn":[0.04741683264],"iteration":980,"passed_time":9.638329779,"remaining_time":0.1866750926},
{"learn":[0.0473922866],"iteration":981,"passed_time":9.647269034,"remaining_time":0.1768338519},
{"learn":[0.04733732037],"iteration":982,"passed_time":9.657104024,"remaining_time":0.1670099373},
{"learn":[0.04723825547],"iteration":983,"passed_time":9.667248132,"remaining_time":0.1571910265},
{"learn":[0.04708944455],"iteration":984,"passed_time":9.676135359,"remaining_time":0.1473523151},
{"learn":[0.04701279543],"iteration":985,"passed_time":9.685400101,"remaining_time":0.1375208939},
{"learn":[0.04694016823],"iteration":986,"passed_time":9.694822321,"remaining_time":0.1276926952},
{"learn":[0.04689073069],"iteration":987,"passed_time":9.703758171,"remaining_time":0.117859411},
{"learn":[0.04685340175],"iteration":988,"passed_time":9.714256391,"remaining_time":0.1080453188},
{"learn":[0.04681200085],"iteration":989,"passed_time":9.722527486,"remaining_time":0.09820734834},
{"learn":[0.04673926245],"iteration":990,"passed_time":9.732660506,"remaining_time":0.0883894496},
{"learn":[0.04667997296],"iteration":991,"passed_time":9.742082322,"remaining_time":0.07856518002},
{"learn":[0.04663099738],"iteration":992,"passed_time":9.751577817,"remaining_time":0.0687422404},
{"learn":[0.0465589241],"iteration":993,"passed_time":9.761996878,"remaining_time":0.05892553448},
{"learn":[0.04645601877],"iteration":994,"passed_time":9.770711104,"remaining_time":0.04909905077},
{"learn":[0.04636902069],"iteration":995,"passed_time":9.78049861,"remaining_time":0.03927911088},
{"learn":[0.04632562969],"iteration":996,"passed_time":9.788887136,"remaining_time":0.02945502649},
{"learn":[0.04627361099],"iteration":997,"passed_time":9.798441297,"remaining_time":0.0196361549},
{"learn":[0.04623192302],"iteration":998,"passed_time":9.808254052,"remaining_time":0.009818072124},
{"learn":[0.04616442895],"iteration":999,"passed_time":9.817383682,"remaining_time":0}
]}